[
  {
    "data_zmiany": "04-05-2026",
    "cena_pln_m3": 6465
  },
  {
    "data_zmiany": "03-05-2026",
    "cena_pln_m3": 6465
  },
  {
    "data_zmiany": "02-05-2026",
    "cena_pln_m3": 6465
  },
  {
    "data_zmiany": "01-05-2026",
    "cena_pln_m3": 6465
  },
  {
    "data_zmiany": "30-04-2026",
    "cena_pln_m3": 6470
  },
  {
    "data_zmiany": "29-04-2026",
    "cena_pln_m3": 6311
  },
  {
    "data_zmiany": "28-04-2026",
    "cena_pln_m3": 6384
  },
  {
    "data_zmiany": "27-04-2026",
    "cena_pln_m3": 6296
  },
  {
    "data_zmiany": "26-04-2026",
    "cena_pln_m3": 6700
  },
  {
    "data_zmiany": "25-04-2026",
    "cena_pln_m3": 6296
  },
  {
    "data_zmiany": "24-04-2026",
    "cena_pln_m3": 6187
  },
  {
    "data_zmiany": "23-04-2026",
    "cena_pln_m3": 5989
  },
  {
    "data_zmiany": "22-04-2026",
    "cena_pln_m3": 5916
  },
  {
    "data_zmiany": "21-04-2026",
    "cena_pln_m3": 6410
  },
  {
    "data_zmiany": "20-04-2026",
    "cena_pln_m3": 6104
  },
  {
    "data_zmiany": "19-04-2026",
    "cena_pln_m3": 6104
  },
  {
    "data_zmiany": "18-04-2026",
    "cena_pln_m3": 6104
  },
  {
    "data_zmiany": "17-04-2026",
    "cena_pln_m3": 6247
  },
  {
    "data_zmiany": "16-04-2026",
    "cena_pln_m3": 6346
  },
  {
    "data_zmiany": "15-04-2026",
    "cena_pln_m3": 6398
  },
  {
    "data_zmiany": "14-04-2026",
    "cena_pln_m3": 6565
  },
  {
    "data_zmiany": "13-04-2026",
    "cena_pln_m3": 6720
  },
  {
    "data_zmiany": "12-04-2026",
    "cena_pln_m3": 6720
  },
  {
    "data_zmiany": "11-04-2026",
    "cena_pln_m3": 6720
  },
  {
    "data_zmiany": "10-04-2026",
    "cena_pln_m3": 6810
  },
  {
    "data_zmiany": "09-04-2026",
    "cena_pln_m3": 6803
  },
  {
    "data_zmiany": "08-04-2026",
    "cena_pln_m3": 6950
  },
  {
    "data_zmiany": "07-04-2026",
    "cena_pln_m3": 6988
  },
  {
    "data_zmiany": "06-04-2026",
    "cena_pln_m3": 6988
  },
  {
    "data_zmiany": "05-04-2026",
    "cena_pln_m3": 6988
  },
  {
    "data_zmiany": "04-04-2026",
    "cena_pln_m3": 6988
  },
  {
    "data_zmiany": "03-04-2026",
    "cena_pln_m3": 6988
  },
  {
    "data_zmiany": "02-04-2026",
    "cena_pln_m3": 6771
  },
  {
    "data_zmiany": "01-04-2026",
    "cena_pln_m3": 6782
  },
  {
    "data_zmiany": "31-03-2026",
    "cena_pln_m3": 6796
  },
  {
    "data_zmiany": "30-03-2026",
    "cena_pln_m3": 6761
  },
  {
    "data_zmiany": "29-03-2026",
    "cena_pln_m3": 7041
  },
  {
    "data_zmiany": "28-03-2026",
    "cena_pln_m3": 7041
  },
  {
    "data_zmiany": "27-03-2026",
    "cena_pln_m3": 6870
  },
  {
    "data_zmiany": "26-03-2026",
    "cena_pln_m3": 6749
  },
  {
    "data_zmiany": "25-03-2026",
    "cena_pln_m3": 7053
  },
  {
    "data_zmiany": "24-03-2026",
    "cena_pln_m3": 7171
  },
  {
    "data_zmiany": "23-03-2026",
    "cena_pln_m3": 7258
  },
  {
    "data_zmiany": "22-03-2026",
    "cena_pln_m3": 7258
  },
  {
    "data_zmiany": "21-03-2026",
    "cena_pln_m3": 7258
  },
  {
    "data_zmiany": "20-03-2026",
    "cena_pln_m3": 6737
  },
  {
    "data_zmiany": "19-03-2026",
    "cena_pln_m3": 6620
  },
  {
    "data_zmiany": "18-03-2026",
    "cena_pln_m3": 6565
  },
  {
    "data_zmiany": "17-03-2026",
    "cena_pln_m3": 6577
  },
  {
    "data_zmiany": "16-03-2026",
    "cena_pln_m3": 6495
  },
  {
    "data_zmiany": "15-03-2026",
    "cena_pln_m3": 6495
  },
  {
    "data_zmiany": "14-03-2026",
    "cena_pln_m3": 6495
  },
  {
    "data_zmiany": "13-03-2026",
    "cena_pln_m3": 6399
  },
  {
    "data_zmiany": "12-03-2026",
    "cena_pln_m3": 6192
  },
  {
    "data_zmiany": "11-03-2026",
    "cena_pln_m3": 6195
  },
  {
    "data_zmiany": "10-03-2026",
    "cena_pln_m3": 6359
  },
  {
    "data_zmiany": "07-03-2026",
    "cena_pln_m3": 6300
  },
  {
    "data_zmiany": "06-03-2026",
    "cena_pln_m3": 6150
  },
  {
    "data_zmiany": "05-03-2026",
    "cena_pln_m3": 5760
  },
  {
    "data_zmiany": "04-03-2026",
    "cena_pln_m3": 5681
  },
  {
    "data_zmiany": "03-03-2026",
    "cena_pln_m3": 5237
  },
  {
    "data_zmiany": "28-02-2026",
    "cena_pln_m3": 4809
  },
  {
    "data_zmiany": "27-02-2026",
    "cena_pln_m3": 4777
  },
  {
    "data_zmiany": "26-02-2026",
    "cena_pln_m3": 4744
  },
  {
    "data_zmiany": "25-02-2026",
    "cena_pln_m3": 4765
  },
  {
    "data_zmiany": "24-02-2026",
    "cena_pln_m3": 4769
  },
  {
    "data_zmiany": "21-02-2026",
    "cena_pln_m3": 4768
  },
  {
    "data_zmiany": "20-02-2026",
    "cena_pln_m3": 4743
  },
  {
    "data_zmiany": "19-02-2026",
    "cena_pln_m3": 4597
  },
  {
    "data_zmiany": "18-02-2026",
    "cena_pln_m3": 4569
  },
  {
    "data_zmiany": "17-02-2026",
    "cena_pln_m3": 4577
  },
  {
    "data_zmiany": "14-02-2026",
    "cena_pln_m3": 4583
  },
  {
    "data_zmiany": "13-02-2026",
    "cena_pln_m3": 4593
  },
  {
    "data_zmiany": "12-02-2026",
    "cena_pln_m3": 4613
  },
  {
    "data_zmiany": "11-02-2026",
    "cena_pln_m3": 4609
  },
  {
    "data_zmiany": "10-02-2026",
    "cena_pln_m3": 4620
  },
  {
    "data_zmiany": "07-02-2026",
    "cena_pln_m3": 4621
  },
  {
    "data_zmiany": "06-02-2026",
    "cena_pln_m3": 4608
  },
  {
    "data_zmiany": "05-02-2026",
    "cena_pln_m3": 4606
  },
  {
    "data_zmiany": "04-02-2026",
    "cena_pln_m3": 4631
  },
  {
    "data_zmiany": "03-02-2026",
    "cena_pln_m3": 4622
  },
  {
    "data_zmiany": "31-01-2026",
    "cena_pln_m3": 4654
  },
  {
    "data_zmiany": "30-01-2026",
    "cena_pln_m3": 4596
  },
  {
    "data_zmiany": "29-01-2026",
    "cena_pln_m3": 4572
  },
  {
    "data_zmiany": "28-01-2026",
    "cena_pln_m3": 4564
  },
  {
    "data_zmiany": "27-01-2026",
    "cena_pln_m3": 4567
  },
  {
    "data_zmiany": "24-01-2026",
    "cena_pln_m3": 4586
  },
  {
    "data_zmiany": "23-01-2026",
    "cena_pln_m3": 4586
  },
  {
    "data_zmiany": "22-01-2026",
    "cena_pln_m3": 4580
  },
  {
    "data_zmiany": "21-01-2026",
    "cena_pln_m3": 4552
  },
  {
    "data_zmiany": "20-01-2026",
    "cena_pln_m3": 4542
  },
  {
    "data_zmiany": "17-01-2026",
    "cena_pln_m3": 4531
  },
  {
    "data_zmiany": "16-01-2026",
    "cena_pln_m3": 4513
  },
  {
    "data_zmiany": "15-01-2026",
    "cena_pln_m3": 4559
  },
  {
    "data_zmiany": "14-01-2026",
    "cena_pln_m3": 4486
  },
  {
    "data_zmiany": "13-01-2026",
    "cena_pln_m3": 4448
  },
  {
    "data_zmiany": "10-01-2026",
    "cena_pln_m3": 4444
  },
  {
    "data_zmiany": "09-01-2026",
    "cena_pln_m3": 4416
  },
  {
    "data_zmiany": "08-01-2026",
    "cena_pln_m3": 4400
  },
  {
    "data_zmiany": "06-01-2026",
    "cena_pln_m3": 4449
  },
  {
    "data_zmiany": "03-01-2026",
    "cena_pln_m3": 4466
  },
  {
    "data_zmiany": "01-01-2026",
    "cena_pln_m3": 4476
  },
  {
    "data_zmiany": "31-12-2025",
    "cena_pln_m3": 4529
  },
  {
    "data_zmiany": "30-12-2025",
    "cena_pln_m3": 4529
  },
  {
    "data_zmiany": "24-12-2025",
    "cena_pln_m3": 4517
  },
  {
    "data_zmiany": "23-12-2025",
    "cena_pln_m3": 4491
  },
  {
    "data_zmiany": "20-12-2025",
    "cena_pln_m3": 4467
  },
  {
    "data_zmiany": "19-12-2025",
    "cena_pln_m3": 4488
  },
  {
    "data_zmiany": "18-12-2025",
    "cena_pln_m3": 4502
  },
  {
    "data_zmiany": "17-12-2025",
    "cena_pln_m3": 4524
  },
  {
    "data_zmiany": "16-12-2025",
    "cena_pln_m3": 4549
  },
  {
    "data_zmiany": "13-12-2025",
    "cena_pln_m3": 4574
  },
  {
    "data_zmiany": "12-12-2025",
    "cena_pln_m3": 4604
  },
  {
    "data_zmiany": "11-12-2025",
    "cena_pln_m3": 4621
  },
  {
    "data_zmiany": "10-12-2025",
    "cena_pln_m3": 4631
  },
  {
    "data_zmiany": "09-12-2025",
    "cena_pln_m3": 4654
  },
  {
    "data_zmiany": "06-12-2025",
    "cena_pln_m3": 4676
  },
  {
    "data_zmiany": "05-12-2025",
    "cena_pln_m3": 4672
  },
  {
    "data_zmiany": "04-12-2025",
    "cena_pln_m3": 4687
  },
  {
    "data_zmiany": "03-12-2025",
    "cena_pln_m3": 4705
  },
  {
    "data_zmiany": "02-12-2025",
    "cena_pln_m3": 4707
  },
  {
    "data_zmiany": "29-11-2025",
    "cena_pln_m3": 4734
  },
  {
    "data_zmiany": "28-11-2025",
    "cena_pln_m3": 4772
  },
  {
    "data_zmiany": "27-11-2025",
    "cena_pln_m3": 4832
  },
  {
    "data_zmiany": "26-11-2025",
    "cena_pln_m3": 4910
  },
  {
    "data_zmiany": "25-11-2025",
    "cena_pln_m3": 4955
  },
  {
    "data_zmiany": "22-11-2025",
    "cena_pln_m3": 4986
  },
  {
    "data_zmiany": "21-11-2025",
    "cena_pln_m3": 5020
  },
  {
    "data_zmiany": "20-11-2025",
    "cena_pln_m3": 5042
  },
  {
    "data_zmiany": "19-11-2025",
    "cena_pln_m3": 5025
  },
  {
    "data_zmiany": "18-11-2025",
    "cena_pln_m3": 4886
  },
  {
    "data_zmiany": "15-11-2025",
    "cena_pln_m3": 4890
  },
  {
    "data_zmiany": "14-11-2025",
    "cena_pln_m3": 4854
  },
  {
    "data_zmiany": "13-11-2025",
    "cena_pln_m3": 4875
  },
  {
    "data_zmiany": "08-11-2025",
    "cena_pln_m3": 4873
  },
  {
    "data_zmiany": "07-11-2025",
    "cena_pln_m3": 4869
  },
  {
    "data_zmiany": "06-11-2025",
    "cena_pln_m3": 4828
  },
  {
    "data_zmiany": "05-11-2025",
    "cena_pln_m3": 4788
  },
  {
    "data_zmiany": "04-11-2025",
    "cena_pln_m3": 4799
  },
  {
    "data_zmiany": "01-11-2025",
    "cena_pln_m3": 4771
  },
  {
    "data_zmiany": "31-10-2025",
    "cena_pln_m3": 4782
  },
  {
    "data_zmiany": "30-10-2025",
    "cena_pln_m3": 4771
  },
  {
    "data_zmiany": "29-10-2025",
    "cena_pln_m3": 4774
  },
  {
    "data_zmiany": "28-10-2025",
    "cena_pln_m3": 4799
  },
  {
    "data_zmiany": "25-10-2025",
    "cena_pln_m3": 4735
  },
  {
    "data_zmiany": "24-10-2025",
    "cena_pln_m3": 4649
  },
  {
    "data_zmiany": "23-10-2025",
    "cena_pln_m3": 4527
  },
  {
    "data_zmiany": "22-10-2025",
    "cena_pln_m3": 4512
  },
  {
    "data_zmiany": "21-10-2025",
    "cena_pln_m3": 4506
  },
  {
    "data_zmiany": "18-10-2025",
    "cena_pln_m3": 4505
  },
  {
    "data_zmiany": "17-10-2025",
    "cena_pln_m3": 4523
  },
  {
    "data_zmiany": "16-10-2025",
    "cena_pln_m3": 4524
  },
  {
    "data_zmiany": "15-10-2025",
    "cena_pln_m3": 4570
  },
  {
    "data_zmiany": "14-10-2025",
    "cena_pln_m3": 4608
  },
  {
    "data_zmiany": "11-10-2025",
    "cena_pln_m3": 4613
  },
  {
    "data_zmiany": "10-10-2025",
    "cena_pln_m3": 4632
  },
  {
    "data_zmiany": "09-10-2025",
    "cena_pln_m3": 4605
  },
  {
    "data_zmiany": "08-10-2025",
    "cena_pln_m3": 4585
  },
  {
    "data_zmiany": "07-10-2025",
    "cena_pln_m3": 4605
  },
  {
    "data_zmiany": "04-10-2025",
    "cena_pln_m3": 4612
  },
  {
    "data_zmiany": "03-10-2025",
    "cena_pln_m3": 4641
  },
  {
    "data_zmiany": "02-10-2025",
    "cena_pln_m3": 4719
  },
  {
    "data_zmiany": "01-10-2025",
    "cena_pln_m3": 4680
  },
  {
    "data_zmiany": "30-09-2025",
    "cena_pln_m3": 4753
  },
  {
    "data_zmiany": "27-09-2025",
    "cena_pln_m3": 4800
  },
  {
    "data_zmiany": "26-09-2025",
    "cena_pln_m3": 4732
  },
  {
    "data_zmiany": "25-09-2025",
    "cena_pln_m3": 4697
  },
  {
    "data_zmiany": "24-09-2025",
    "cena_pln_m3": 4682
  },
  {
    "data_zmiany": "23-09-2025",
    "cena_pln_m3": 4678
  },
  {
    "data_zmiany": "20-09-2025",
    "cena_pln_m3": 4689
  },
  {
    "data_zmiany": "19-09-2025",
    "cena_pln_m3": 4690
  },
  {
    "data_zmiany": "18-09-2025",
    "cena_pln_m3": 4681
  },
  {
    "data_zmiany": "17-09-2025",
    "cena_pln_m3": 4678
  },
  {
    "data_zmiany": "16-09-2025",
    "cena_pln_m3": 4664
  },
  {
    "data_zmiany": "13-09-2025",
    "cena_pln_m3": 4657
  },
  {
    "data_zmiany": "12-09-2025",
    "cena_pln_m3": 4641
  },
  {
    "data_zmiany": "11-09-2025",
    "cena_pln_m3": 4686
  },
  {
    "data_zmiany": "10-09-2025",
    "cena_pln_m3": 4678
  },
  {
    "data_zmiany": "09-09-2025",
    "cena_pln_m3": 4650
  },
  {
    "data_zmiany": "06-09-2025",
    "cena_pln_m3": 4639
  },
  {
    "data_zmiany": "05-09-2025",
    "cena_pln_m3": 4677
  },
  {
    "data_zmiany": "04-09-2025",
    "cena_pln_m3": 4664
  },
  {
    "data_zmiany": "03-09-2025",
    "cena_pln_m3": 4647
  },
  {
    "data_zmiany": "02-09-2025",
    "cena_pln_m3": 4628
  },
  {
    "data_zmiany": "30-08-2025",
    "cena_pln_m3": 4624
  },
  {
    "data_zmiany": "29-08-2025",
    "cena_pln_m3": 4628
  },
  {
    "data_zmiany": "28-08-2025",
    "cena_pln_m3": 4630
  },
  {
    "data_zmiany": "27-08-2025",
    "cena_pln_m3": 4614
  },
  {
    "data_zmiany": "23-08-2025",
    "cena_pln_m3": 4610
  },
  {
    "data_zmiany": "22-08-2025",
    "cena_pln_m3": 4571
  },
  {
    "data_zmiany": "21-08-2025",
    "cena_pln_m3": 4554
  },
  {
    "data_zmiany": "20-08-2025",
    "cena_pln_m3": 4537
  },
  {
    "data_zmiany": "19-08-2025",
    "cena_pln_m3": 4520
  },
  {
    "data_zmiany": "15-08-2025",
    "cena_pln_m3": 4532
  },
  {
    "data_zmiany": "14-08-2025",
    "cena_pln_m3": 4520
  },
  {
    "data_zmiany": "13-08-2025",
    "cena_pln_m3": 4581
  },
  {
    "data_zmiany": "12-08-2025",
    "cena_pln_m3": 4591
  },
  {
    "data_zmiany": "09-08-2025",
    "cena_pln_m3": 4594
  },
  {
    "data_zmiany": "08-08-2025",
    "cena_pln_m3": 4582
  },
  {
    "data_zmiany": "07-08-2025",
    "cena_pln_m3": 4640
  },
  {
    "data_zmiany": "06-08-2025",
    "cena_pln_m3": 4625
  },
  {
    "data_zmiany": "05-08-2025",
    "cena_pln_m3": 4667
  },
  {
    "data_zmiany": "02-08-2025",
    "cena_pln_m3": 4691
  },
  {
    "data_zmiany": "01-08-2025",
    "cena_pln_m3": 4750
  },
  {
    "data_zmiany": "31-07-2025",
    "cena_pln_m3": 4741
  },
  {
    "data_zmiany": "30-07-2025",
    "cena_pln_m3": 4737
  },
  {
    "data_zmiany": "29-07-2025",
    "cena_pln_m3": 4732
  },
  {
    "data_zmiany": "26-07-2025",
    "cena_pln_m3": 4729
  },
  {
    "data_zmiany": "25-07-2025",
    "cena_pln_m3": 4715
  },
  {
    "data_zmiany": "24-07-2025",
    "cena_pln_m3": 4733
  },
  {
    "data_zmiany": "23-07-2025",
    "cena_pln_m3": 4753
  },
  {
    "data_zmiany": "22-07-2025",
    "cena_pln_m3": 4790
  },
  {
    "data_zmiany": "19-07-2025",
    "cena_pln_m3": 4782
  },
  {
    "data_zmiany": "18-07-2025",
    "cena_pln_m3": 4769
  },
  {
    "data_zmiany": "17-07-2025",
    "cena_pln_m3": 4754
  },
  {
    "data_zmiany": "16-07-2025",
    "cena_pln_m3": 4770
  },
  {
    "data_zmiany": "15-07-2025",
    "cena_pln_m3": 4809
  },
  {
    "data_zmiany": "12-07-2025",
    "cena_pln_m3": 4822
  },
  {
    "data_zmiany": "11-07-2025",
    "cena_pln_m3": 4790
  },
  {
    "data_zmiany": "10-07-2025",
    "cena_pln_m3": 4812
  },
  {
    "data_zmiany": "09-07-2025",
    "cena_pln_m3": 4814
  },
  {
    "data_zmiany": "08-07-2025",
    "cena_pln_m3": 4796
  },
  {
    "data_zmiany": "05-07-2025",
    "cena_pln_m3": 4775
  },
  {
    "data_zmiany": "04-07-2025",
    "cena_pln_m3": 4737
  },
  {
    "data_zmiany": "03-07-2025",
    "cena_pln_m3": 4656
  },
  {
    "data_zmiany": "02-07-2025",
    "cena_pln_m3": 4632
  },
  {
    "data_zmiany": "01-07-2025",
    "cena_pln_m3": 4627
  },
  {
    "data_zmiany": "28-06-2025",
    "cena_pln_m3": 4649
  },
  {
    "data_zmiany": "27-06-2025",
    "cena_pln_m3": 4668
  },
  {
    "data_zmiany": "26-06-2025",
    "cena_pln_m3": 4743
  },
  {
    "data_zmiany": "25-06-2025",
    "cena_pln_m3": 4848
  },
  {
    "data_zmiany": "24-06-2025",
    "cena_pln_m3": 4987
  },
  {
    "data_zmiany": "21-06-2025",
    "cena_pln_m3": 4953
  },
  {
    "data_zmiany": "19-06-2025",
    "cena_pln_m3": 4892
  },
  {
    "data_zmiany": "18-06-2025",
    "cena_pln_m3": 4855
  },
  {
    "data_zmiany": "17-06-2025",
    "cena_pln_m3": 4714
  },
  {
    "data_zmiany": "14-06-2025",
    "cena_pln_m3": 4655
  },
  {
    "data_zmiany": "13-06-2025",
    "cena_pln_m3": 4561
  },
  {
    "data_zmiany": "12-06-2025",
    "cena_pln_m3": 4552
  },
  {
    "data_zmiany": "11-06-2025",
    "cena_pln_m3": 4538
  },
  {
    "data_zmiany": "10-06-2025",
    "cena_pln_m3": 4528
  },
  {
    "data_zmiany": "07-06-2025",
    "cena_pln_m3": 4513
  },
  {
    "data_zmiany": "06-06-2025",
    "cena_pln_m3": 4496
  },
  {
    "data_zmiany": "05-06-2025",
    "cena_pln_m3": 4489
  },
  {
    "data_zmiany": "04-06-2025",
    "cena_pln_m3": 4485
  },
  {
    "data_zmiany": "03-06-2025",
    "cena_pln_m3": 4474
  },
  {
    "data_zmiany": "31-05-2025",
    "cena_pln_m3": 4470
  },
  {
    "data_zmiany": "30-05-2025",
    "cena_pln_m3": 4487
  },
  {
    "data_zmiany": "29-05-2025",
    "cena_pln_m3": 4488
  },
  {
    "data_zmiany": "28-05-2025",
    "cena_pln_m3": 4464
  },
  {
    "data_zmiany": "24-05-2025",
    "cena_pln_m3": 4490
  },
  {
    "data_zmiany": "23-05-2025",
    "cena_pln_m3": 4478
  },
  {
    "data_zmiany": "22-05-2025",
    "cena_pln_m3": 4483
  },
  {
    "data_zmiany": "21-05-2025",
    "cena_pln_m3": 4497
  },
  {
    "data_zmiany": "20-05-2025",
    "cena_pln_m3": 4530
  },
  {
    "data_zmiany": "17-05-2025",
    "cena_pln_m3": 4526
  },
  {
    "data_zmiany": "16-05-2025",
    "cena_pln_m3": 4530
  },
  {
    "data_zmiany": "15-05-2025",
    "cena_pln_m3": 4543
  },
  {
    "data_zmiany": "14-05-2025",
    "cena_pln_m3": 4541
  },
  {
    "data_zmiany": "13-05-2025",
    "cena_pln_m3": 4487
  },
  {
    "data_zmiany": "10-05-2025",
    "cena_pln_m3": 4461
  },
  {
    "data_zmiany": "09-05-2025",
    "cena_pln_m3": 4438
  },
  {
    "data_zmiany": "08-05-2025",
    "cena_pln_m3": 4425
  },
  {
    "data_zmiany": "07-05-2025",
    "cena_pln_m3": 4444
  },
  {
    "data_zmiany": "01-05-2025",
    "cena_pln_m3": 4506
  },
  {
    "data_zmiany": "30-04-2025",
    "cena_pln_m3": 4517
  },
  {
    "data_zmiany": "29-04-2025",
    "cena_pln_m3": 4524
  },
  {
    "data_zmiany": "26-04-2025",
    "cena_pln_m3": 4532
  },
  {
    "data_zmiany": "25-04-2025",
    "cena_pln_m3": 4519
  },
  {
    "data_zmiany": "24-04-2025",
    "cena_pln_m3": 4520
  },
  {
    "data_zmiany": "23-04-2025",
    "cena_pln_m3": 4526
  },
  {
    "data_zmiany": "18-04-2025",
    "cena_pln_m3": 4536
  },
  {
    "data_zmiany": "17-04-2025",
    "cena_pln_m3": 4496
  },
  {
    "data_zmiany": "16-04-2025",
    "cena_pln_m3": 4477
  },
  {
    "data_zmiany": "15-04-2025",
    "cena_pln_m3": 4476
  },
  {
    "data_zmiany": "12-04-2025",
    "cena_pln_m3": 4474
  },
  {
    "data_zmiany": "11-04-2025",
    "cena_pln_m3": 4509
  },
  {
    "data_zmiany": "10-04-2025",
    "cena_pln_m3": 4504
  },
  {
    "data_zmiany": "09-04-2025",
    "cena_pln_m3": 4564
  },
  {
    "data_zmiany": "08-04-2025",
    "cena_pln_m3": 4616
  },
  {
    "data_zmiany": "05-04-2025",
    "cena_pln_m3": 4692
  },
  {
    "data_zmiany": "04-04-2025",
    "cena_pln_m3": 4731
  },
  {
    "data_zmiany": "03-04-2025",
    "cena_pln_m3": 4776
  },
  {
    "data_zmiany": "02-04-2025",
    "cena_pln_m3": 4773
  },
  {
    "data_zmiany": "01-04-2025",
    "cena_pln_m3": 4770
  },
  {
    "data_zmiany": "29-03-2025",
    "cena_pln_m3": 4755
  },
  {
    "data_zmiany": "28-03-2025",
    "cena_pln_m3": 4770
  },
  {
    "data_zmiany": "27-03-2025",
    "cena_pln_m3": 4759
  },
  {
    "data_zmiany": "26-03-2025",
    "cena_pln_m3": 4736
  },
  {
    "data_zmiany": "25-03-2025",
    "cena_pln_m3": 4737
  },
  {
    "data_zmiany": "22-03-2025",
    "cena_pln_m3": 4741
  },
  {
    "data_zmiany": "21-03-2025",
    "cena_pln_m3": 4706
  },
  {
    "data_zmiany": "20-03-2025",
    "cena_pln_m3": 4658
  },
  {
    "data_zmiany": "19-03-2025",
    "cena_pln_m3": 4658
  },
  {
    "data_zmiany": "18-03-2025",
    "cena_pln_m3": 4651
  },
  {
    "data_zmiany": "15-03-2025",
    "cena_pln_m3": 4654
  },
  {
    "data_zmiany": "14-03-2025",
    "cena_pln_m3": 4665
  },
  {
    "data_zmiany": "13-03-2025",
    "cena_pln_m3": 4703
  },
  {
    "data_zmiany": "12-03-2025",
    "cena_pln_m3": 4695
  },
  {
    "data_zmiany": "11-03-2025",
    "cena_pln_m3": 4692
  },
  {
    "data_zmiany": "08-03-2025",
    "cena_pln_m3": 4720
  },
  {
    "data_zmiany": "07-03-2025",
    "cena_pln_m3": 4712
  },
  {
    "data_zmiany": "06-03-2025",
    "cena_pln_m3": 4749
  },
  {
    "data_zmiany": "05-03-2025",
    "cena_pln_m3": 4847
  },
  {
    "data_zmiany": "04-03-2025",
    "cena_pln_m3": 4884
  },
  {
    "data_zmiany": "01-03-2025",
    "cena_pln_m3": 4891
  },
  {
    "data_zmiany": "28-02-2025",
    "cena_pln_m3": 4850
  },
  {
    "data_zmiany": "27-02-2025",
    "cena_pln_m3": 4842
  },
  {
    "data_zmiany": "26-02-2025",
    "cena_pln_m3": 4899
  },
  {
    "data_zmiany": "25-02-2025",
    "cena_pln_m3": 4951
  },
  {
    "data_zmiany": "22-02-2025",
    "cena_pln_m3": 4976
  },
  {
    "data_zmiany": "21-02-2025",
    "cena_pln_m3": 5013
  },
  {
    "data_zmiany": "20-02-2025",
    "cena_pln_m3": 4960
  },
  {
    "data_zmiany": "19-02-2025",
    "cena_pln_m3": 4941
  },
  {
    "data_zmiany": "18-02-2025",
    "cena_pln_m3": 4935
  },
  {
    "data_zmiany": "15-02-2025",
    "cena_pln_m3": 4960
  },
  {
    "data_zmiany": "14-02-2025",
    "cena_pln_m3": 4937
  },
  {
    "data_zmiany": "13-02-2025",
    "cena_pln_m3": 5011
  },
  {
    "data_zmiany": "12-02-2025",
    "cena_pln_m3": 5014
  },
  {
    "data_zmiany": "11-02-2025",
    "cena_pln_m3": 4950
  },
  {
    "data_zmiany": "08-02-2025",
    "cena_pln_m3": 4923
  },
  {
    "data_zmiany": "07-02-2025",
    "cena_pln_m3": 4918
  },
  {
    "data_zmiany": "06-02-2025",
    "cena_pln_m3": 4915
  },
  {
    "data_zmiany": "05-02-2025",
    "cena_pln_m3": 4995
  },
  {
    "data_zmiany": "04-02-2025",
    "cena_pln_m3": 4974
  },
  {
    "data_zmiany": "01-02-2025",
    "cena_pln_m3": 4934
  },
  {
    "data_zmiany": "31-01-2025",
    "cena_pln_m3": 4935
  },
  {
    "data_zmiany": "30-01-2025",
    "cena_pln_m3": 4943
  },
  {
    "data_zmiany": "29-01-2025",
    "cena_pln_m3": 4957
  },
  {
    "data_zmiany": "28-01-2025",
    "cena_pln_m3": 4987
  },
  {
    "data_zmiany": "25-01-2025",
    "cena_pln_m3": 5031
  },
  {
    "data_zmiany": "24-01-2025",
    "cena_pln_m3": 5070
  },
  {
    "data_zmiany": "23-01-2025",
    "cena_pln_m3": 5110
  },
  {
    "data_zmiany": "22-01-2025",
    "cena_pln_m3": 5136
  },
  {
    "data_zmiany": "21-01-2025",
    "cena_pln_m3": 5145
  },
  {
    "data_zmiany": "18-01-2025",
    "cena_pln_m3": 5153
  },
  {
    "data_zmiany": "17-01-2025",
    "cena_pln_m3": 5154
  },
  {
    "data_zmiany": "16-01-2025",
    "cena_pln_m3": 5159
  },
  {
    "data_zmiany": "15-01-2025",
    "cena_pln_m3": 5143
  },
  {
    "data_zmiany": "14-01-2025",
    "cena_pln_m3": 5144
  },
  {
    "data_zmiany": "11-01-2025",
    "cena_pln_m3": 5016
  },
  {
    "data_zmiany": "10-01-2025",
    "cena_pln_m3": 4969
  },
  {
    "data_zmiany": "09-01-2025",
    "cena_pln_m3": 4943
  },
  {
    "data_zmiany": "08-01-2025",
    "cena_pln_m3": 4960
  },
  {
    "data_zmiany": "04-01-2025",
    "cena_pln_m3": 4965
  },
  {
    "data_zmiany": "03-01-2025",
    "cena_pln_m3": 4956
  },
  {
    "data_zmiany": "01-01-2025",
    "cena_pln_m3": 4922
  },
  {
    "data_zmiany": "31-12-2024",
    "cena_pln_m3": 4910
  },
  {
    "data_zmiany": "28-12-2024",
    "cena_pln_m3": 4879
  },
  {
    "data_zmiany": "25-12-2024",
    "cena_pln_m3": 4867
  },
  {
    "data_zmiany": "24-12-2024",
    "cena_pln_m3": 4867
  },
  {
    "data_zmiany": "21-12-2024",
    "cena_pln_m3": 4878
  },
  {
    "data_zmiany": "20-12-2024",
    "cena_pln_m3": 4874
  },
  {
    "data_zmiany": "19-12-2024",
    "cena_pln_m3": 4867
  },
  {
    "data_zmiany": "18-12-2024",
    "cena_pln_m3": 4855
  },
  {
    "data_zmiany": "17-12-2024",
    "cena_pln_m3": 4864
  },
  {
    "data_zmiany": "14-12-2024",
    "cena_pln_m3": 4852
  },
  {
    "data_zmiany": "13-12-2024",
    "cena_pln_m3": 4821
  },
  {
    "data_zmiany": "12-12-2024",
    "cena_pln_m3": 4805
  },
  {
    "data_zmiany": "11-12-2024",
    "cena_pln_m3": 4788
  },
  {
    "data_zmiany": "10-12-2024",
    "cena_pln_m3": 4779
  },
  {
    "data_zmiany": "07-12-2024",
    "cena_pln_m3": 4786
  },
  {
    "data_zmiany": "06-12-2024",
    "cena_pln_m3": 4823
  },
  {
    "data_zmiany": "05-12-2024",
    "cena_pln_m3": 4837
  },
  {
    "data_zmiany": "04-12-2024",
    "cena_pln_m3": 4841
  },
  {
    "data_zmiany": "03-12-2024",
    "cena_pln_m3": 4833
  },
  {
    "data_zmiany": "30-11-2024",
    "cena_pln_m3": 4873
  },
  {
    "data_zmiany": "29-11-2024",
    "cena_pln_m3": 4902
  },
  {
    "data_zmiany": "28-11-2024",
    "cena_pln_m3": 4926
  },
  {
    "data_zmiany": "27-11-2024",
    "cena_pln_m3": 4943
  },
  {
    "data_zmiany": "26-11-2024",
    "cena_pln_m3": 4950
  },
  {
    "data_zmiany": "23-11-2024",
    "cena_pln_m3": 4996
  },
  {
    "data_zmiany": "22-11-2024",
    "cena_pln_m3": 4951
  },
  {
    "data_zmiany": "21-11-2024",
    "cena_pln_m3": 4920
  },
  {
    "data_zmiany": "20-11-2024",
    "cena_pln_m3": 4927
  },
  {
    "data_zmiany": "19-11-2024",
    "cena_pln_m3": 4919
  },
  {
    "data_zmiany": "16-11-2024",
    "cena_pln_m3": 4886
  },
  {
    "data_zmiany": "15-11-2024",
    "cena_pln_m3": 4905
  },
  {
    "data_zmiany": "14-11-2024",
    "cena_pln_m3": 4867
  },
  {
    "data_zmiany": "13-11-2024",
    "cena_pln_m3": 4872
  },
  {
    "data_zmiany": "09-11-2024",
    "cena_pln_m3": 4857
  },
  {
    "data_zmiany": "08-11-2024",
    "cena_pln_m3": 4874
  },
  {
    "data_zmiany": "07-11-2024",
    "cena_pln_m3": 4896
  },
  {
    "data_zmiany": "06-11-2024",
    "cena_pln_m3": 4875
  },
  {
    "data_zmiany": "05-11-2024",
    "cena_pln_m3": 4823
  },
  {
    "data_zmiany": "01-11-2024",
    "cena_pln_m3": 4782
  },
  {
    "data_zmiany": "31-10-2024",
    "cena_pln_m3": 4741
  },
  {
    "data_zmiany": "30-10-2024",
    "cena_pln_m3": 4743
  },
  {
    "data_zmiany": "29-10-2024",
    "cena_pln_m3": 4760
  },
  {
    "data_zmiany": "26-10-2024",
    "cena_pln_m3": 4802
  },
  {
    "data_zmiany": "25-10-2024",
    "cena_pln_m3": 4770
  },
  {
    "data_zmiany": "24-10-2024",
    "cena_pln_m3": 4772
  },
  {
    "data_zmiany": "23-10-2024",
    "cena_pln_m3": 4764
  },
  {
    "data_zmiany": "22-10-2024",
    "cena_pln_m3": 4695
  },
  {
    "data_zmiany": "19-10-2024",
    "cena_pln_m3": 4703
  },
  {
    "data_zmiany": "18-10-2024",
    "cena_pln_m3": 4737
  },
  {
    "data_zmiany": "17-10-2024",
    "cena_pln_m3": 4711
  },
  {
    "data_zmiany": "16-10-2024",
    "cena_pln_m3": 4764
  },
  {
    "data_zmiany": "15-10-2024",
    "cena_pln_m3": 4811
  },
  {
    "data_zmiany": "12-10-2024",
    "cena_pln_m3": 4837
  },
  {
    "data_zmiany": "11-10-2024",
    "cena_pln_m3": 4821
  },
  {
    "data_zmiany": "10-10-2024",
    "cena_pln_m3": 4821
  },
  {
    "data_zmiany": "09-10-2024",
    "cena_pln_m3": 4837
  },
  {
    "data_zmiany": "08-10-2024",
    "cena_pln_m3": 4894
  },
  {
    "data_zmiany": "05-10-2024",
    "cena_pln_m3": 4789
  },
  {
    "data_zmiany": "04-10-2024",
    "cena_pln_m3": 4707
  },
  {
    "data_zmiany": "03-10-2024",
    "cena_pln_m3": 4648
  },
  {
    "data_zmiany": "02-10-2024",
    "cena_pln_m3": 4640
  },
  {
    "data_zmiany": "01-10-2024",
    "cena_pln_m3": 4596
  },
  {
    "data_zmiany": "28-09-2024",
    "cena_pln_m3": 4591
  },
  {
    "data_zmiany": "27-09-2024",
    "cena_pln_m3": 4592
  },
  {
    "data_zmiany": "26-09-2024",
    "cena_pln_m3": 4614
  },
  {
    "data_zmiany": "25-09-2024",
    "cena_pln_m3": 4609
  },
  {
    "data_zmiany": "24-09-2024",
    "cena_pln_m3": 4598
  },
  {
    "data_zmiany": "21-09-2024",
    "cena_pln_m3": 4587
  },
  {
    "data_zmiany": "20-09-2024",
    "cena_pln_m3": 4581
  },
  {
    "data_zmiany": "19-09-2024",
    "cena_pln_m3": 4569
  },
  {
    "data_zmiany": "18-09-2024",
    "cena_pln_m3": 4560
  },
  {
    "data_zmiany": "17-09-2024",
    "cena_pln_m3": 4553
  },
  {
    "data_zmiany": "14-09-2024",
    "cena_pln_m3": 4583
  },
  {
    "data_zmiany": "13-09-2024",
    "cena_pln_m3": 4595
  },
  {
    "data_zmiany": "12-09-2024",
    "cena_pln_m3": 4546
  },
  {
    "data_zmiany": "11-09-2024",
    "cena_pln_m3": 4555
  },
  {
    "data_zmiany": "10-09-2024",
    "cena_pln_m3": 4589
  },
  {
    "data_zmiany": "07-09-2024",
    "cena_pln_m3": 4586
  },
  {
    "data_zmiany": "06-09-2024",
    "cena_pln_m3": 4643
  },
  {
    "data_zmiany": "05-09-2024",
    "cena_pln_m3": 4676
  },
  {
    "data_zmiany": "04-09-2024",
    "cena_pln_m3": 4716
  },
  {
    "data_zmiany": "03-09-2024",
    "cena_pln_m3": 4737
  },
  {
    "data_zmiany": "31-08-2024",
    "cena_pln_m3": 4744
  },
  {
    "data_zmiany": "30-08-2024",
    "cena_pln_m3": 4728
  },
  {
    "data_zmiany": "29-08-2024",
    "cena_pln_m3": 4720
  },
  {
    "data_zmiany": "28-08-2024",
    "cena_pln_m3": 4720
  },
  {
    "data_zmiany": "24-08-2024",
    "cena_pln_m3": 4716
  },
  {
    "data_zmiany": "23-08-2024",
    "cena_pln_m3": 4706
  },
  {
    "data_zmiany": "22-08-2024",
    "cena_pln_m3": 4706
  },
  {
    "data_zmiany": "21-08-2024",
    "cena_pln_m3": 4690
  },
  {
    "data_zmiany": "20-08-2024",
    "cena_pln_m3": 4756
  },
  {
    "data_zmiany": "17-08-2024",
    "cena_pln_m3": 4833
  },
  {
    "data_zmiany": "15-08-2024",
    "cena_pln_m3": 4864
  },
  {
    "data_zmiany": "14-08-2024",
    "cena_pln_m3": 4884
  },
  {
    "data_zmiany": "13-08-2024",
    "cena_pln_m3": 4875
  },
  {
    "data_zmiany": "10-08-2024",
    "cena_pln_m3": 4856
  },
  {
    "data_zmiany": "09-08-2024",
    "cena_pln_m3": 4840
  },
  {
    "data_zmiany": "08-08-2024",
    "cena_pln_m3": 4837
  },
  {
    "data_zmiany": "07-08-2024",
    "cena_pln_m3": 4819
  },
  {
    "data_zmiany": "06-08-2024",
    "cena_pln_m3": 4825
  },
  {
    "data_zmiany": "03-08-2024",
    "cena_pln_m3": 4902
  },
  {
    "data_zmiany": "02-08-2024",
    "cena_pln_m3": 4922
  },
  {
    "data_zmiany": "01-08-2024",
    "cena_pln_m3": 4930
  },
  {
    "data_zmiany": "31-07-2024",
    "cena_pln_m3": 4874
  },
  {
    "data_zmiany": "30-07-2024",
    "cena_pln_m3": 4944
  },
  {
    "data_zmiany": "27-07-2024",
    "cena_pln_m3": 4953
  },
  {
    "data_zmiany": "26-07-2024",
    "cena_pln_m3": 4963
  },
  {
    "data_zmiany": "25-07-2024",
    "cena_pln_m3": 4945
  },
  {
    "data_zmiany": "24-07-2024",
    "cena_pln_m3": 4920
  },
  {
    "data_zmiany": "23-07-2024",
    "cena_pln_m3": 4936
  },
  {
    "data_zmiany": "20-07-2024",
    "cena_pln_m3": 4980
  },
  {
    "data_zmiany": "19-07-2024",
    "cena_pln_m3": 4982
  },
  {
    "data_zmiany": "18-07-2024",
    "cena_pln_m3": 4977
  },
  {
    "data_zmiany": "17-07-2024",
    "cena_pln_m3": 4968
  },
  {
    "data_zmiany": "16-07-2024",
    "cena_pln_m3": 5001
  },
  {
    "data_zmiany": "13-07-2024",
    "cena_pln_m3": 5034
  },
  {
    "data_zmiany": "12-07-2024",
    "cena_pln_m3": 5039
  },
  {
    "data_zmiany": "11-07-2024",
    "cena_pln_m3": 5037
  },
  {
    "data_zmiany": "10-07-2024",
    "cena_pln_m3": 5042
  },
  {
    "data_zmiany": "09-07-2024",
    "cena_pln_m3": 5136
  },
  {
    "data_zmiany": "06-07-2024",
    "cena_pln_m3": 5190
  },
  {
    "data_zmiany": "05-07-2024",
    "cena_pln_m3": 5188
  },
  {
    "data_zmiany": "04-07-2024",
    "cena_pln_m3": 5186
  },
  {
    "data_zmiany": "03-07-2024",
    "cena_pln_m3": 5184
  },
  {
    "data_zmiany": "02-07-2024",
    "cena_pln_m3": 5163
  },
  {
    "data_zmiany": "29-06-2024",
    "cena_pln_m3": 5162
  },
  {
    "data_zmiany": "28-06-2024",
    "cena_pln_m3": 5161
  },
  {
    "data_zmiany": "27-06-2024",
    "cena_pln_m3": 5148
  },
  {
    "data_zmiany": "26-06-2024",
    "cena_pln_m3": 5142
  },
  {
    "data_zmiany": "25-06-2024",
    "cena_pln_m3": 5152
  },
  {
    "data_zmiany": "22-06-2024",
    "cena_pln_m3": 5169
  },
  {
    "data_zmiany": "21-06-2024",
    "cena_pln_m3": 5160
  },
  {
    "data_zmiany": "20-06-2024",
    "cena_pln_m3": 5148
  },
  {
    "data_zmiany": "19-06-2024",
    "cena_pln_m3": 5117
  },
  {
    "data_zmiany": "18-06-2024",
    "cena_pln_m3": 5090
  },
  {
    "data_zmiany": "15-06-2024",
    "cena_pln_m3": 5062
  },
  {
    "data_zmiany": "14-06-2024",
    "cena_pln_m3": 5013
  },
  {
    "data_zmiany": "13-06-2024",
    "cena_pln_m3": 4979
  },
  {
    "data_zmiany": "12-06-2024",
    "cena_pln_m3": 4943
  },
  {
    "data_zmiany": "11-06-2024",
    "cena_pln_m3": 4906
  },
  {
    "data_zmiany": "08-06-2024",
    "cena_pln_m3": 4881
  },
  {
    "data_zmiany": "07-06-2024",
    "cena_pln_m3": 4874
  },
  {
    "data_zmiany": "06-06-2024",
    "cena_pln_m3": 4858
  },
  {
    "data_zmiany": "05-06-2024",
    "cena_pln_m3": 4857
  },
  {
    "data_zmiany": "04-06-2024",
    "cena_pln_m3": 4906
  },
  {
    "data_zmiany": "01-06-2024",
    "cena_pln_m3": 4935
  },
  {
    "data_zmiany": "30-05-2024",
    "cena_pln_m3": 4977
  },
  {
    "data_zmiany": "29-05-2024",
    "cena_pln_m3": 4975
  },
  {
    "data_zmiany": "25-05-2024",
    "cena_pln_m3": 4957
  },
  {
    "data_zmiany": "24-05-2024",
    "cena_pln_m3": 4967
  },
  {
    "data_zmiany": "23-05-2024",
    "cena_pln_m3": 4958
  },
  {
    "data_zmiany": "22-05-2024",
    "cena_pln_m3": 4978
  },
  {
    "data_zmiany": "21-05-2024",
    "cena_pln_m3": 4972
  },
  {
    "data_zmiany": "18-05-2024",
    "cena_pln_m3": 4966
  },
  {
    "data_zmiany": "17-05-2024",
    "cena_pln_m3": 4951
  },
  {
    "data_zmiany": "16-05-2024",
    "cena_pln_m3": 4970
  },
  {
    "data_zmiany": "15-05-2024",
    "cena_pln_m3": 5007
  },
  {
    "data_zmiany": "14-05-2024",
    "cena_pln_m3": 5028
  },
  {
    "data_zmiany": "11-05-2024",
    "cena_pln_m3": 5028
  },
  {
    "data_zmiany": "10-05-2024",
    "cena_pln_m3": 5033
  },
  {
    "data_zmiany": "09-05-2024",
    "cena_pln_m3": 5030
  },
  {
    "data_zmiany": "08-05-2024",
    "cena_pln_m3": 5043
  },
  {
    "data_zmiany": "03-05-2024",
    "cena_pln_m3": 5090
  },
  {
    "data_zmiany": "01-05-2024",
    "cena_pln_m3": 5127
  },
  {
    "data_zmiany": "30-04-2024",
    "cena_pln_m3": 5135
  },
  {
    "data_zmiany": "27-04-2024",
    "cena_pln_m3": 5142
  },
  {
    "data_zmiany": "26-04-2024",
    "cena_pln_m3": 5132
  },
  {
    "data_zmiany": "25-04-2024",
    "cena_pln_m3": 5139
  },
  {
    "data_zmiany": "24-04-2024",
    "cena_pln_m3": 5162
  },
  {
    "data_zmiany": "23-04-2024",
    "cena_pln_m3": 5188
  },
  {
    "data_zmiany": "20-04-2024",
    "cena_pln_m3": 5211
  },
  {
    "data_zmiany": "19-04-2024",
    "cena_pln_m3": 5244
  },
  {
    "data_zmiany": "18-04-2024",
    "cena_pln_m3": 5271
  },
  {
    "data_zmiany": "17-04-2024",
    "cena_pln_m3": 5273
  },
  {
    "data_zmiany": "16-04-2024",
    "cena_pln_m3": 5265
  },
  {
    "data_zmiany": "13-04-2024",
    "cena_pln_m3": 5259
  },
  {
    "data_zmiany": "12-04-2024",
    "cena_pln_m3": 5224
  },
  {
    "data_zmiany": "11-04-2024",
    "cena_pln_m3": 5248
  },
  {
    "data_zmiany": "10-04-2024",
    "cena_pln_m3": 5307
  },
  {
    "data_zmiany": "09-04-2024",
    "cena_pln_m3": 5349
  },
  {
    "data_zmiany": "06-04-2024",
    "cena_pln_m3": 5366
  },
  {
    "data_zmiany": "05-04-2024",
    "cena_pln_m3": 5340
  },
  {
    "data_zmiany": "04-04-2024",
    "cena_pln_m3": 5347
  },
  {
    "data_zmiany": "03-04-2024",
    "cena_pln_m3": 5288
  },
  {
    "data_zmiany": "29-03-2024",
    "cena_pln_m3": 5268
  },
  {
    "data_zmiany": "28-03-2024",
    "cena_pln_m3": 5230
  },
  {
    "data_zmiany": "27-03-2024",
    "cena_pln_m3": 5246
  },
  {
    "data_zmiany": "26-03-2024",
    "cena_pln_m3": 5264
  },
  {
    "data_zmiany": "23-03-2024",
    "cena_pln_m3": 5271
  },
  {
    "data_zmiany": "22-03-2024",
    "cena_pln_m3": 5241
  },
  {
    "data_zmiany": "21-03-2024",
    "cena_pln_m3": 5308
  },
  {
    "data_zmiany": "20-03-2024",
    "cena_pln_m3": 5338
  },
  {
    "data_zmiany": "19-03-2024",
    "cena_pln_m3": 5298
  },
  {
    "data_zmiany": "16-03-2024",
    "cena_pln_m3": 5246
  },
  {
    "data_zmiany": "15-03-2024",
    "cena_pln_m3": 5191
  },
  {
    "data_zmiany": "14-03-2024",
    "cena_pln_m3": 5172
  },
  {
    "data_zmiany": "13-03-2024",
    "cena_pln_m3": 5160
  },
  {
    "data_zmiany": "12-03-2024",
    "cena_pln_m3": 5201
  },
  {
    "data_zmiany": "09-03-2024",
    "cena_pln_m3": 5211
  },
  {
    "data_zmiany": "08-03-2024",
    "cena_pln_m3": 5228
  },
  {
    "data_zmiany": "07-03-2024",
    "cena_pln_m3": 5249
  },
  {
    "data_zmiany": "06-03-2024",
    "cena_pln_m3": 5247
  },
  {
    "data_zmiany": "05-03-2024",
    "cena_pln_m3": 5266
  },
  {
    "data_zmiany": "02-03-2024",
    "cena_pln_m3": 5275
  },
  {
    "data_zmiany": "01-03-2024",
    "cena_pln_m3": 5255
  },
  {
    "data_zmiany": "29-02-2024",
    "cena_pln_m3": 5270
  },
  {
    "data_zmiany": "28-02-2024",
    "cena_pln_m3": 5292
  },
  {
    "data_zmiany": "27-02-2024",
    "cena_pln_m3": 5294
  },
  {
    "data_zmiany": "24-02-2024",
    "cena_pln_m3": 5291
  },
  {
    "data_zmiany": "23-02-2024",
    "cena_pln_m3": 5298
  },
  {
    "data_zmiany": "22-02-2024",
    "cena_pln_m3": 5334
  },
  {
    "data_zmiany": "21-02-2024",
    "cena_pln_m3": 5361
  },
  {
    "data_zmiany": "20-02-2024",
    "cena_pln_m3": 5414
  },
  {
    "data_zmiany": "17-02-2024",
    "cena_pln_m3": 5432
  },
  {
    "data_zmiany": "16-02-2024",
    "cena_pln_m3": 5452
  },
  {
    "data_zmiany": "15-02-2024",
    "cena_pln_m3": 5461
  },
  {
    "data_zmiany": "14-02-2024",
    "cena_pln_m3": 5459
  },
  {
    "data_zmiany": "13-02-2024",
    "cena_pln_m3": 5433
  },
  {
    "data_zmiany": "10-02-2024",
    "cena_pln_m3": 5395
  },
  {
    "data_zmiany": "09-02-2024",
    "cena_pln_m3": 5366
  },
  {
    "data_zmiany": "08-02-2024",
    "cena_pln_m3": 5273
  },
  {
    "data_zmiany": "07-02-2024",
    "cena_pln_m3": 5251
  },
  {
    "data_zmiany": "06-02-2024",
    "cena_pln_m3": 5233
  },
  {
    "data_zmiany": "03-02-2024",
    "cena_pln_m3": 5268
  },
  {
    "data_zmiany": "02-02-2024",
    "cena_pln_m3": 5319
  },
  {
    "data_zmiany": "01-02-2024",
    "cena_pln_m3": 5310
  },
  {
    "data_zmiany": "31-01-2024",
    "cena_pln_m3": 5288
  },
  {
    "data_zmiany": "30-01-2024",
    "cena_pln_m3": 5269
  },
  {
    "data_zmiany": "27-01-2024",
    "cena_pln_m3": 5232
  },
  {
    "data_zmiany": "26-01-2024",
    "cena_pln_m3": 5211
  },
  {
    "data_zmiany": "25-01-2024",
    "cena_pln_m3": 5194
  },
  {
    "data_zmiany": "24-01-2024",
    "cena_pln_m3": 5181
  },
  {
    "data_zmiany": "23-01-2024",
    "cena_pln_m3": 5171
  },
  {
    "data_zmiany": "20-01-2024",
    "cena_pln_m3": 5167
  },
  {
    "data_zmiany": "19-01-2024",
    "cena_pln_m3": 5152
  },
  {
    "data_zmiany": "18-01-2024",
    "cena_pln_m3": 5136
  },
  {
    "data_zmiany": "17-01-2024",
    "cena_pln_m3": 5116
  },
  {
    "data_zmiany": "16-01-2024",
    "cena_pln_m3": 5084
  },
  {
    "data_zmiany": "13-01-2024",
    "cena_pln_m3": 5060
  },
  {
    "data_zmiany": "12-01-2024",
    "cena_pln_m3": 5048
  },
  {
    "data_zmiany": "11-01-2024",
    "cena_pln_m3": 5026
  },
  {
    "data_zmiany": "10-01-2024",
    "cena_pln_m3": 5029
  },
  {
    "data_zmiany": "09-01-2024",
    "cena_pln_m3": 5022
  },
  {
    "data_zmiany": "06-01-2024",
    "cena_pln_m3": 5020
  },
  {
    "data_zmiany": "05-01-2024",
    "cena_pln_m3": 5012
  },
  {
    "data_zmiany": "04-01-2024",
    "cena_pln_m3": 5024
  },
  {
    "data_zmiany": "03-01-2024",
    "cena_pln_m3": 4995
  },
  {
    "data_zmiany": "01-01-2024",
    "cena_pln_m3": 5018
  },
  {
    "data_zmiany": "30-12-2023",
    "cena_pln_m3": 4965
  },
  {
    "data_zmiany": "29-12-2023",
    "cena_pln_m3": 5009
  },
  {
    "data_zmiany": "28-12-2023",
    "cena_pln_m3": 5049
  },
  {
    "data_zmiany": "23-12-2023",
    "cena_pln_m3": 5082
  },
  {
    "data_zmiany": "22-12-2023",
    "cena_pln_m3": 5090
  },
  {
    "data_zmiany": "21-12-2023",
    "cena_pln_m3": 5082
  },
  {
    "data_zmiany": "20-12-2023",
    "cena_pln_m3": 5039
  },
  {
    "data_zmiany": "19-12-2023",
    "cena_pln_m3": 4991
  },
  {
    "data_zmiany": "16-12-2023",
    "cena_pln_m3": 4950
  },
  {
    "data_zmiany": "15-12-2023",
    "cena_pln_m3": 4944
  },
  {
    "data_zmiany": "14-12-2023",
    "cena_pln_m3": 4944
  },
  {
    "data_zmiany": "13-12-2023",
    "cena_pln_m3": 4970
  },
  {
    "data_zmiany": "12-12-2023",
    "cena_pln_m3": 5006
  },
  {
    "data_zmiany": "09-12-2023",
    "cena_pln_m3": 5005
  },
  {
    "data_zmiany": "08-12-2023",
    "cena_pln_m3": 5007
  },
  {
    "data_zmiany": "07-12-2023",
    "cena_pln_m3": 5030
  },
  {
    "data_zmiany": "06-12-2023",
    "cena_pln_m3": 5054
  },
  {
    "data_zmiany": "05-12-2023",
    "cena_pln_m3": 5055
  },
  {
    "data_zmiany": "02-12-2023",
    "cena_pln_m3": 5114
  },
  {
    "data_zmiany": "01-12-2023",
    "cena_pln_m3": 5135
  },
  {
    "data_zmiany": "30-11-2023",
    "cena_pln_m3": 5160
  },
  {
    "data_zmiany": "29-11-2023",
    "cena_pln_m3": 5172
  },
  {
    "data_zmiany": "28-11-2023",
    "cena_pln_m3": 5150
  },
  {
    "data_zmiany": "25-11-2023",
    "cena_pln_m3": 5223
  },
  {
    "data_zmiany": "24-11-2023",
    "cena_pln_m3": 5211
  },
  {
    "data_zmiany": "23-11-2023",
    "cena_pln_m3": 5199
  },
  {
    "data_zmiany": "22-11-2023",
    "cena_pln_m3": 5195
  },
  {
    "data_zmiany": "21-11-2023",
    "cena_pln_m3": 5187
  },
  {
    "data_zmiany": "18-11-2023",
    "cena_pln_m3": 5174
  },
  {
    "data_zmiany": "17-11-2023",
    "cena_pln_m3": 5202
  },
  {
    "data_zmiany": "16-11-2023",
    "cena_pln_m3": 5246
  },
  {
    "data_zmiany": "15-11-2023",
    "cena_pln_m3": 5276
  },
  {
    "data_zmiany": "14-11-2023",
    "cena_pln_m3": 5273
  },
  {
    "data_zmiany": "10-11-2023",
    "cena_pln_m3": 5303
  },
  {
    "data_zmiany": "09-11-2023",
    "cena_pln_m3": 5347
  },
  {
    "data_zmiany": "08-11-2023",
    "cena_pln_m3": 5376
  },
  {
    "data_zmiany": "07-11-2023",
    "cena_pln_m3": 5390
  },
  {
    "data_zmiany": "04-11-2023",
    "cena_pln_m3": 5338
  },
  {
    "data_zmiany": "03-11-2023",
    "cena_pln_m3": 5279
  },
  {
    "data_zmiany": "01-11-2023",
    "cena_pln_m3": 5221
  },
  {
    "data_zmiany": "31-10-2023",
    "cena_pln_m3": 5171
  },
  {
    "data_zmiany": "28-10-2023",
    "cena_pln_m3": 5118
  },
  {
    "data_zmiany": "27-10-2023",
    "cena_pln_m3": 5064
  },
  {
    "data_zmiany": "26-10-2023",
    "cena_pln_m3": 5010
  },
  {
    "data_zmiany": "25-10-2023",
    "cena_pln_m3": 4951
  },
  {
    "data_zmiany": "24-10-2023",
    "cena_pln_m3": 4904
  },
  {
    "data_zmiany": "21-10-2023",
    "cena_pln_m3": 4840
  },
  {
    "data_zmiany": "20-10-2023",
    "cena_pln_m3": 4821
  },
  {
    "data_zmiany": "19-10-2023",
    "cena_pln_m3": 4791
  },
  {
    "data_zmiany": "18-10-2023",
    "cena_pln_m3": 4779
  },
  {
    "data_zmiany": "17-10-2023",
    "cena_pln_m3": 4779
  },
  {
    "data_zmiany": "14-10-2023",
    "cena_pln_m3": 4758
  },
  {
    "data_zmiany": "13-10-2023",
    "cena_pln_m3": 4758
  },
  {
    "data_zmiany": "12-10-2023",
    "cena_pln_m3": 4758
  },
  {
    "data_zmiany": "11-10-2023",
    "cena_pln_m3": 4758
  },
  {
    "data_zmiany": "10-10-2023",
    "cena_pln_m3": 4753
  },
  {
    "data_zmiany": "07-10-2023",
    "cena_pln_m3": 4753
  },
  {
    "data_zmiany": "06-10-2023",
    "cena_pln_m3": 4751
  },
  {
    "data_zmiany": "05-10-2023",
    "cena_pln_m3": 4752
  },
  {
    "data_zmiany": "04-10-2023",
    "cena_pln_m3": 4749
  },
  {
    "data_zmiany": "03-10-2023",
    "cena_pln_m3": 4748
  },
  {
    "data_zmiany": "30-09-2023",
    "cena_pln_m3": 4749
  },
  {
    "data_zmiany": "29-09-2023",
    "cena_pln_m3": 4746
  },
  {
    "data_zmiany": "28-09-2023",
    "cena_pln_m3": 4746
  },
  {
    "data_zmiany": "27-09-2023",
    "cena_pln_m3": 4746
  },
  {
    "data_zmiany": "26-09-2023",
    "cena_pln_m3": 4749
  },
  {
    "data_zmiany": "23-09-2023",
    "cena_pln_m3": 4752
  },
  {
    "data_zmiany": "22-09-2023",
    "cena_pln_m3": 4755
  },
  {
    "data_zmiany": "21-09-2023",
    "cena_pln_m3": 4757
  },
  {
    "data_zmiany": "20-09-2023",
    "cena_pln_m3": 4757
  },
  {
    "data_zmiany": "19-09-2023",
    "cena_pln_m3": 4756
  },
  {
    "data_zmiany": "16-09-2023",
    "cena_pln_m3": 4832
  },
  {
    "data_zmiany": "15-09-2023",
    "cena_pln_m3": 4869
  },
  {
    "data_zmiany": "14-09-2023",
    "cena_pln_m3": 4897
  },
  {
    "data_zmiany": "13-09-2023",
    "cena_pln_m3": 4929
  },
  {
    "data_zmiany": "12-09-2023",
    "cena_pln_m3": 4969
  },
  {
    "data_zmiany": "09-09-2023",
    "cena_pln_m3": 5009
  },
  {
    "data_zmiany": "08-09-2023",
    "cena_pln_m3": 5039
  },
  {
    "data_zmiany": "07-09-2023",
    "cena_pln_m3": 5069
  },
  {
    "data_zmiany": "06-09-2023",
    "cena_pln_m3": 5099
  },
  {
    "data_zmiany": "05-09-2023",
    "cena_pln_m3": 5129
  },
  {
    "data_zmiany": "02-09-2023",
    "cena_pln_m3": 5129
  },
  {
    "data_zmiany": "01-09-2023",
    "cena_pln_m3": 5100
  },
  {
    "data_zmiany": "31-08-2023",
    "cena_pln_m3": 5173
  },
  {
    "data_zmiany": "30-08-2023",
    "cena_pln_m3": 5212
  },
  {
    "data_zmiany": "26-08-2023",
    "cena_pln_m3": 5241
  },
  {
    "data_zmiany": "25-08-2023",
    "cena_pln_m3": 5241
  },
  {
    "data_zmiany": "24-08-2023",
    "cena_pln_m3": 5233
  },
  {
    "data_zmiany": "23-08-2023",
    "cena_pln_m3": 5242
  },
  {
    "data_zmiany": "22-08-2023",
    "cena_pln_m3": 5252
  },
  {
    "data_zmiany": "19-08-2023",
    "cena_pln_m3": 5229
  },
  {
    "data_zmiany": "18-08-2023",
    "cena_pln_m3": 5203
  },
  {
    "data_zmiany": "17-08-2023",
    "cena_pln_m3": 5200
  },
  {
    "data_zmiany": "15-08-2023",
    "cena_pln_m3": 5202
  },
  {
    "data_zmiany": "12-08-2023",
    "cena_pln_m3": 5224
  },
  {
    "data_zmiany": "11-08-2023",
    "cena_pln_m3": 5224
  },
  {
    "data_zmiany": "10-08-2023",
    "cena_pln_m3": 5224
  },
  {
    "data_zmiany": "09-08-2023",
    "cena_pln_m3": 5206
  },
  {
    "data_zmiany": "08-08-2023",
    "cena_pln_m3": 5233
  },
  {
    "data_zmiany": "05-08-2023",
    "cena_pln_m3": 5234
  },
  {
    "data_zmiany": "04-08-2023",
    "cena_pln_m3": 5236
  },
  {
    "data_zmiany": "03-08-2023",
    "cena_pln_m3": 5235
  },
  {
    "data_zmiany": "02-08-2023",
    "cena_pln_m3": 5234
  },
  {
    "data_zmiany": "01-08-2023",
    "cena_pln_m3": 5236
  },
  {
    "data_zmiany": "29-07-2023",
    "cena_pln_m3": 5236
  },
  {
    "data_zmiany": "28-07-2023",
    "cena_pln_m3": 5235
  },
  {
    "data_zmiany": "27-07-2023",
    "cena_pln_m3": 5213
  },
  {
    "data_zmiany": "26-07-2023",
    "cena_pln_m3": 5172
  },
  {
    "data_zmiany": "25-07-2023",
    "cena_pln_m3": 5129
  },
  {
    "data_zmiany": "22-07-2023",
    "cena_pln_m3": 5071
  },
  {
    "data_zmiany": "21-07-2023",
    "cena_pln_m3": 5042
  },
  {
    "data_zmiany": "20-07-2023",
    "cena_pln_m3": 5033
  },
  {
    "data_zmiany": "19-07-2023",
    "cena_pln_m3": 5007
  },
  {
    "data_zmiany": "18-07-2023",
    "cena_pln_m3": 4999
  },
  {
    "data_zmiany": "15-07-2023",
    "cena_pln_m3": 5023
  },
  {
    "data_zmiany": "14-07-2023",
    "cena_pln_m3": 5032
  },
  {
    "data_zmiany": "13-07-2023",
    "cena_pln_m3": 5040
  },
  {
    "data_zmiany": "12-07-2023",
    "cena_pln_m3": 5033
  },
  {
    "data_zmiany": "11-07-2023",
    "cena_pln_m3": 5016
  },
  {
    "data_zmiany": "08-07-2023",
    "cena_pln_m3": 4996
  },
  {
    "data_zmiany": "07-07-2023",
    "cena_pln_m3": 4976
  },
  {
    "data_zmiany": "06-07-2023",
    "cena_pln_m3": 4959
  },
  {
    "data_zmiany": "05-07-2023",
    "cena_pln_m3": 4937
  },
  {
    "data_zmiany": "04-07-2023",
    "cena_pln_m3": 4930
  },
  {
    "data_zmiany": "01-07-2023",
    "cena_pln_m3": 4927
  },
  {
    "data_zmiany": "30-06-2023",
    "cena_pln_m3": 4902
  },
  {
    "data_zmiany": "29-06-2023",
    "cena_pln_m3": 4919
  },
  {
    "data_zmiany": "28-06-2023",
    "cena_pln_m3": 4923
  },
  {
    "data_zmiany": "27-06-2023",
    "cena_pln_m3": 4932
  },
  {
    "data_zmiany": "24-06-2023",
    "cena_pln_m3": 4934
  },
  {
    "data_zmiany": "23-06-2023",
    "cena_pln_m3": 4952
  },
  {
    "data_zmiany": "22-06-2023",
    "cena_pln_m3": 5011
  },
  {
    "data_zmiany": "21-06-2023",
    "cena_pln_m3": 4972
  },
  {
    "data_zmiany": "20-06-2023",
    "cena_pln_m3": 5002
  },
  {
    "data_zmiany": "17-06-2023",
    "cena_pln_m3": 4954
  },
  {
    "data_zmiany": "16-06-2023",
    "cena_pln_m3": 4944
  },
  {
    "data_zmiany": "15-06-2023",
    "cena_pln_m3": 4946
  },
  {
    "data_zmiany": "14-06-2023",
    "cena_pln_m3": 4934
  },
  {
    "data_zmiany": "13-06-2023",
    "cena_pln_m3": 4886
  },
  {
    "data_zmiany": "10-06-2023",
    "cena_pln_m3": 4969
  },
  {
    "data_zmiany": "08-06-2023",
    "cena_pln_m3": 4972
  },
  {
    "data_zmiany": "07-06-2023",
    "cena_pln_m3": 4947
  },
  {
    "data_zmiany": "06-06-2023",
    "cena_pln_m3": 4928
  },
  {
    "data_zmiany": "03-06-2023",
    "cena_pln_m3": 4912
  },
  {
    "data_zmiany": "02-06-2023",
    "cena_pln_m3": 4899
  },
  {
    "data_zmiany": "01-06-2023",
    "cena_pln_m3": 4897
  },
  {
    "data_zmiany": "31-05-2023",
    "cena_pln_m3": 4906
  },
  {
    "data_zmiany": "27-05-2023",
    "cena_pln_m3": 4909
  },
  {
    "data_zmiany": "26-05-2023",
    "cena_pln_m3": 4884
  },
  {
    "data_zmiany": "25-05-2023",
    "cena_pln_m3": 4906
  },
  {
    "data_zmiany": "24-05-2023",
    "cena_pln_m3": 4897
  },
  {
    "data_zmiany": "23-05-2023",
    "cena_pln_m3": 4900
  },
  {
    "data_zmiany": "20-05-2023",
    "cena_pln_m3": 4906
  },
  {
    "data_zmiany": "19-05-2023",
    "cena_pln_m3": 4908
  },
  {
    "data_zmiany": "18-05-2023",
    "cena_pln_m3": 4921
  },
  {
    "data_zmiany": "17-05-2023",
    "cena_pln_m3": 4863
  },
  {
    "data_zmiany": "16-05-2023",
    "cena_pln_m3": 4874
  },
  {
    "data_zmiany": "13-05-2023",
    "cena_pln_m3": 4881
  },
  {
    "data_zmiany": "12-05-2023",
    "cena_pln_m3": 4881
  },
  {
    "data_zmiany": "11-05-2023",
    "cena_pln_m3": 4881
  },
  {
    "data_zmiany": "10-05-2023",
    "cena_pln_m3": 4832
  },
  {
    "data_zmiany": "06-05-2023",
    "cena_pln_m3": 4794
  },
  {
    "data_zmiany": "05-05-2023",
    "cena_pln_m3": 4793
  },
  {
    "data_zmiany": "03-05-2023",
    "cena_pln_m3": 4910
  },
  {
    "data_zmiany": "29-04-2023",
    "cena_pln_m3": 4939
  },
  {
    "data_zmiany": "28-04-2023",
    "cena_pln_m3": 4916
  },
  {
    "data_zmiany": "27-04-2023",
    "cena_pln_m3": 4980
  },
  {
    "data_zmiany": "26-04-2023",
    "cena_pln_m3": 5038
  },
  {
    "data_zmiany": "25-04-2023",
    "cena_pln_m3": 5099
  },
  {
    "data_zmiany": "22-04-2023",
    "cena_pln_m3": 5098
  },
  {
    "data_zmiany": "21-04-2023",
    "cena_pln_m3": 5083
  },
  {
    "data_zmiany": "20-04-2023",
    "cena_pln_m3": 5224
  },
  {
    "data_zmiany": "19-04-2023",
    "cena_pln_m3": 5246
  },
  {
    "data_zmiany": "18-04-2023",
    "cena_pln_m3": 5269
  },
  {
    "data_zmiany": "15-04-2023",
    "cena_pln_m3": 5338
  },
  {
    "data_zmiany": "14-04-2023",
    "cena_pln_m3": 5367
  },
  {
    "data_zmiany": "13-04-2023",
    "cena_pln_m3": 5381
  },
  {
    "data_zmiany": "12-04-2023",
    "cena_pln_m3": 5389
  },
  {
    "data_zmiany": "07-04-2023",
    "cena_pln_m3": 5408
  },
  {
    "data_zmiany": "06-04-2023",
    "cena_pln_m3": 5386
  },
  {
    "data_zmiany": "05-04-2023",
    "cena_pln_m3": 5376
  },
  {
    "data_zmiany": "04-04-2023",
    "cena_pln_m3": 5374
  },
  {
    "data_zmiany": "01-04-2023",
    "cena_pln_m3": 5334
  },
  {
    "data_zmiany": "31-03-2023",
    "cena_pln_m3": 5328
  },
  {
    "data_zmiany": "30-03-2023",
    "cena_pln_m3": 5360
  },
  {
    "data_zmiany": "29-03-2023",
    "cena_pln_m3": 5403
  },
  {
    "data_zmiany": "28-03-2023",
    "cena_pln_m3": 5392
  },
  {
    "data_zmiany": "25-03-2023",
    "cena_pln_m3": 5390
  },
  {
    "data_zmiany": "24-03-2023",
    "cena_pln_m3": 5385
  },
  {
    "data_zmiany": "23-03-2023",
    "cena_pln_m3": 5421
  },
  {
    "data_zmiany": "22-03-2023",
    "cena_pln_m3": 5412
  },
  {
    "data_zmiany": "21-03-2023",
    "cena_pln_m3": 5412
  },
  {
    "data_zmiany": "18-03-2023",
    "cena_pln_m3": 5394
  },
  {
    "data_zmiany": "17-03-2023",
    "cena_pln_m3": 5346
  },
  {
    "data_zmiany": "16-03-2023",
    "cena_pln_m3": 5312
  },
  {
    "data_zmiany": "15-03-2023",
    "cena_pln_m3": 5539
  },
  {
    "data_zmiany": "14-03-2023",
    "cena_pln_m3": 5560
  },
  {
    "data_zmiany": "11-03-2023",
    "cena_pln_m3": 5606
  },
  {
    "data_zmiany": "10-03-2023",
    "cena_pln_m3": 5583
  },
  {
    "data_zmiany": "09-03-2023",
    "cena_pln_m3": 5721
  },
  {
    "data_zmiany": "08-03-2023",
    "cena_pln_m3": 5743
  },
  {
    "data_zmiany": "07-03-2023",
    "cena_pln_m3": 5764
  },
  {
    "data_zmiany": "04-03-2023",
    "cena_pln_m3": 5763
  },
  {
    "data_zmiany": "03-03-2023",
    "cena_pln_m3": 5761
  },
  {
    "data_zmiany": "02-03-2023",
    "cena_pln_m3": 5763
  },
  {
    "data_zmiany": "01-03-2023",
    "cena_pln_m3": 5786
  },
  {
    "data_zmiany": "28-02-2023",
    "cena_pln_m3": 5715
  },
  {
    "data_zmiany": "25-02-2023",
    "cena_pln_m3": 5694
  },
  {
    "data_zmiany": "24-02-2023",
    "cena_pln_m3": 5686
  },
  {
    "data_zmiany": "23-02-2023",
    "cena_pln_m3": 5710
  },
  {
    "data_zmiany": "22-02-2023",
    "cena_pln_m3": 5730
  },
  {
    "data_zmiany": "21-02-2023",
    "cena_pln_m3": 5767
  },
  {
    "data_zmiany": "18-02-2023",
    "cena_pln_m3": 5805
  },
  {
    "data_zmiany": "17-02-2023",
    "cena_pln_m3": 5836
  },
  {
    "data_zmiany": "16-02-2023",
    "cena_pln_m3": 5852
  },
  {
    "data_zmiany": "15-02-2023",
    "cena_pln_m3": 5885
  },
  {
    "data_zmiany": "14-02-2023",
    "cena_pln_m3": 5891
  },
  {
    "data_zmiany": "11-02-2023",
    "cena_pln_m3": 5851
  },
  {
    "data_zmiany": "10-02-2023",
    "cena_pln_m3": 5805
  },
  {
    "data_zmiany": "09-02-2023",
    "cena_pln_m3": 5833
  },
  {
    "data_zmiany": "08-02-2023",
    "cena_pln_m3": 5837
  },
  {
    "data_zmiany": "07-02-2023",
    "cena_pln_m3": 5786
  },
  {
    "data_zmiany": "04-02-2023",
    "cena_pln_m3": 5807
  },
  {
    "data_zmiany": "03-02-2023",
    "cena_pln_m3": 5890
  },
  {
    "data_zmiany": "02-02-2023",
    "cena_pln_m3": 5982
  },
  {
    "data_zmiany": "01-02-2023",
    "cena_pln_m3": 6037
  },
  {
    "data_zmiany": "31-01-2023",
    "cena_pln_m3": 6095
  },
  {
    "data_zmiany": "28-01-2023",
    "cena_pln_m3": 6177
  },
  {
    "data_zmiany": "27-01-2023",
    "cena_pln_m3": 6214
  },
  {
    "data_zmiany": "26-01-2023",
    "cena_pln_m3": 6219
  },
  {
    "data_zmiany": "25-01-2023",
    "cena_pln_m3": 6223
  },
  {
    "data_zmiany": "24-01-2023",
    "cena_pln_m3": 6245
  },
  {
    "data_zmiany": "21-01-2023",
    "cena_pln_m3": 6200
  },
  {
    "data_zmiany": "20-01-2023",
    "cena_pln_m3": 6186
  },
  {
    "data_zmiany": "19-01-2023",
    "cena_pln_m3": 6203
  },
  {
    "data_zmiany": "18-01-2023",
    "cena_pln_m3": 6160
  },
  {
    "data_zmiany": "17-01-2023",
    "cena_pln_m3": 6111
  },
  {
    "data_zmiany": "14-01-2023",
    "cena_pln_m3": 6096
  },
  {
    "data_zmiany": "13-01-2023",
    "cena_pln_m3": 6071
  },
  {
    "data_zmiany": "12-01-2023",
    "cena_pln_m3": 6007
  },
  {
    "data_zmiany": "11-01-2023",
    "cena_pln_m3": 6011
  },
  {
    "data_zmiany": "10-01-2023",
    "cena_pln_m3": 6020
  },
  {
    "data_zmiany": "06-01-2023",
    "cena_pln_m3": 6045
  },
  {
    "data_zmiany": "05-01-2023",
    "cena_pln_m3": 6081
  },
  {
    "data_zmiany": "04-01-2023",
    "cena_pln_m3": 6113
  },
  {
    "data_zmiany": "01-01-2023",
    "cena_pln_m3": 6094
  },
  {
    "data_zmiany": "31-12-2022",
    "cena_pln_m3": 6057
  },
  {
    "data_zmiany": "30-12-2022",
    "cena_pln_m3": 6895
  },
  {
    "data_zmiany": "29-12-2022",
    "cena_pln_m3": 6900
  },
  {
    "data_zmiany": "24-12-2022",
    "cena_pln_m3": 6823
  },
  {
    "data_zmiany": "23-12-2022",
    "cena_pln_m3": 6789
  },
  {
    "data_zmiany": "22-12-2022",
    "cena_pln_m3": 6786
  },
  {
    "data_zmiany": "21-12-2022",
    "cena_pln_m3": 6797
  },
  {
    "data_zmiany": "20-12-2022",
    "cena_pln_m3": 6809
  },
  {
    "data_zmiany": "17-12-2022",
    "cena_pln_m3": 6819
  },
  {
    "data_zmiany": "16-12-2022",
    "cena_pln_m3": 6832
  },
  {
    "data_zmiany": "15-12-2022",
    "cena_pln_m3": 6812
  },
  {
    "data_zmiany": "14-12-2022",
    "cena_pln_m3": 6745
  },
  {
    "data_zmiany": "13-12-2022",
    "cena_pln_m3": 6579
  },
  {
    "data_zmiany": "10-12-2022",
    "cena_pln_m3": 6542
  },
  {
    "data_zmiany": "09-12-2022",
    "cena_pln_m3": 6537
  },
  {
    "data_zmiany": "08-12-2022",
    "cena_pln_m3": 6569
  },
  {
    "data_zmiany": "07-12-2022",
    "cena_pln_m3": 6586
  },
  {
    "data_zmiany": "06-12-2022",
    "cena_pln_m3": 6599
  },
  {
    "data_zmiany": "03-12-2022",
    "cena_pln_m3": 6615
  },
  {
    "data_zmiany": "02-12-2022",
    "cena_pln_m3": 6622
  },
  {
    "data_zmiany": "01-12-2022",
    "cena_pln_m3": 6559
  },
  {
    "data_zmiany": "30-11-2022",
    "cena_pln_m3": 6535
  },
  {
    "data_zmiany": "29-11-2022",
    "cena_pln_m3": 6526
  },
  {
    "data_zmiany": "26-11-2022",
    "cena_pln_m3": 6499
  },
  {
    "data_zmiany": "25-11-2022",
    "cena_pln_m3": 6510
  },
  {
    "data_zmiany": "24-11-2022",
    "cena_pln_m3": 6527
  },
  {
    "data_zmiany": "23-11-2022",
    "cena_pln_m3": 6553
  },
  {
    "data_zmiany": "22-11-2022",
    "cena_pln_m3": 6539
  },
  {
    "data_zmiany": "19-11-2022",
    "cena_pln_m3": 6577
  },
  {
    "data_zmiany": "18-11-2022",
    "cena_pln_m3": 6599
  },
  {
    "data_zmiany": "17-11-2022",
    "cena_pln_m3": 6646
  },
  {
    "data_zmiany": "16-11-2022",
    "cena_pln_m3": 6679
  },
  {
    "data_zmiany": "15-11-2022",
    "cena_pln_m3": 6745
  },
  {
    "data_zmiany": "11-11-2022",
    "cena_pln_m3": 6985
  },
  {
    "data_zmiany": "10-11-2022",
    "cena_pln_m3": 7084
  },
  {
    "data_zmiany": "09-11-2022",
    "cena_pln_m3": 7125
  },
  {
    "data_zmiany": "08-11-2022",
    "cena_pln_m3": 7161
  },
  {
    "data_zmiany": "05-11-2022",
    "cena_pln_m3": 7221
  },
  {
    "data_zmiany": "04-11-2022",
    "cena_pln_m3": 7238
  },
  {
    "data_zmiany": "03-11-2022",
    "cena_pln_m3": 7138
  },
  {
    "data_zmiany": "01-11-2022",
    "cena_pln_m3": 7275
  },
  {
    "data_zmiany": "29-10-2022",
    "cena_pln_m3": 7343
  },
  {
    "data_zmiany": "28-10-2022",
    "cena_pln_m3": 7323
  },
  {
    "data_zmiany": "27-10-2022",
    "cena_pln_m3": 7352
  },
  {
    "data_zmiany": "26-10-2022",
    "cena_pln_m3": 7367
  },
  {
    "data_zmiany": "25-10-2022",
    "cena_pln_m3": 7384
  },
  {
    "data_zmiany": "22-10-2022",
    "cena_pln_m3": 7383
  },
  {
    "data_zmiany": "21-10-2022",
    "cena_pln_m3": 7419
  },
  {
    "data_zmiany": "20-10-2022",
    "cena_pln_m3": 7454
  },
  {
    "data_zmiany": "19-10-2022",
    "cena_pln_m3": 7487
  },
  {
    "data_zmiany": "18-10-2022",
    "cena_pln_m3": 7513
  },
  {
    "data_zmiany": "15-10-2022",
    "cena_pln_m3": 7510
  },
  {
    "data_zmiany": "14-10-2022",
    "cena_pln_m3": 7557
  },
  {
    "data_zmiany": "13-10-2022",
    "cena_pln_m3": 7536
  },
  {
    "data_zmiany": "12-10-2022",
    "cena_pln_m3": 7548
  },
  {
    "data_zmiany": "11-10-2022",
    "cena_pln_m3": 7669
  },
  {
    "data_zmiany": "08-10-2022",
    "cena_pln_m3": 7672
  },
  {
    "data_zmiany": "07-10-2022",
    "cena_pln_m3": 7381
  },
  {
    "data_zmiany": "06-10-2022",
    "cena_pln_m3": 7280
  },
  {
    "data_zmiany": "05-10-2022",
    "cena_pln_m3": 6977
  },
  {
    "data_zmiany": "04-10-2022",
    "cena_pln_m3": 6756
  },
  {
    "data_zmiany": "01-10-2022",
    "cena_pln_m3": 6748
  },
  {
    "data_zmiany": "30-09-2022",
    "cena_pln_m3": 6780
  },
  {
    "data_zmiany": "29-09-2022",
    "cena_pln_m3": 6765
  },
  {
    "data_zmiany": "28-09-2022",
    "cena_pln_m3": 6526
  },
  {
    "data_zmiany": "27-09-2022",
    "cena_pln_m3": 6468
  },
  {
    "data_zmiany": "24-09-2022",
    "cena_pln_m3": 6524
  },
  {
    "data_zmiany": "23-09-2022",
    "cena_pln_m3": 6580
  },
  {
    "data_zmiany": "22-09-2022",
    "cena_pln_m3": 6427
  },
  {
    "data_zmiany": "21-09-2022",
    "cena_pln_m3": 6392
  },
  {
    "data_zmiany": "17-09-2022",
    "cena_pln_m3": 6461
  },
  {
    "data_zmiany": "16-09-2022",
    "cena_pln_m3": 6521
  },
  {
    "data_zmiany": "15-09-2022",
    "cena_pln_m3": 6614
  },
  {
    "data_zmiany": "14-09-2022",
    "cena_pln_m3": 6676
  },
  {
    "data_zmiany": "13-09-2022",
    "cena_pln_m3": 6722
  },
  {
    "data_zmiany": "10-09-2022",
    "cena_pln_m3": 6754
  },
  {
    "data_zmiany": "09-09-2022",
    "cena_pln_m3": 6785
  },
  {
    "data_zmiany": "08-09-2022",
    "cena_pln_m3": 6827
  },
  {
    "data_zmiany": "07-09-2022",
    "cena_pln_m3": 6852
  },
  {
    "data_zmiany": "06-09-2022",
    "cena_pln_m3": 6893
  },
  {
    "data_zmiany": "03-09-2022",
    "cena_pln_m3": 6875
  },
  {
    "data_zmiany": "02-09-2022",
    "cena_pln_m3": 6963
  },
  {
    "data_zmiany": "01-09-2022",
    "cena_pln_m3": 7048
  },
  {
    "data_zmiany": "31-08-2022",
    "cena_pln_m3": 7067
  },
  {
    "data_zmiany": "27-08-2022",
    "cena_pln_m3": 7206
  },
  {
    "data_zmiany": "26-08-2022",
    "cena_pln_m3": 7155
  },
  {
    "data_zmiany": "25-08-2022",
    "cena_pln_m3": 7085
  },
  {
    "data_zmiany": "24-08-2022",
    "cena_pln_m3": 6979
  },
  {
    "data_zmiany": "23-08-2022",
    "cena_pln_m3": 6877
  },
  {
    "data_zmiany": "20-08-2022",
    "cena_pln_m3": 6811
  },
  {
    "data_zmiany": "19-08-2022",
    "cena_pln_m3": 6743
  },
  {
    "data_zmiany": "18-08-2022",
    "cena_pln_m3": 6670
  },
  {
    "data_zmiany": "17-08-2022",
    "cena_pln_m3": 6621
  },
  {
    "data_zmiany": "13-08-2022",
    "cena_pln_m3": 6517
  },
  {
    "data_zmiany": "12-08-2022",
    "cena_pln_m3": 6456
  },
  {
    "data_zmiany": "11-08-2022",
    "cena_pln_m3": 6442
  },
  {
    "data_zmiany": "10-08-2022",
    "cena_pln_m3": 6460
  },
  {
    "data_zmiany": "09-08-2022",
    "cena_pln_m3": 6464
  },
  {
    "data_zmiany": "06-08-2022",
    "cena_pln_m3": 6514
  },
  {
    "data_zmiany": "05-08-2022",
    "cena_pln_m3": 6552
  },
  {
    "data_zmiany": "04-08-2022",
    "cena_pln_m3": 6566
  },
  {
    "data_zmiany": "03-08-2022",
    "cena_pln_m3": 6617
  },
  {
    "data_zmiany": "02-08-2022",
    "cena_pln_m3": 6776
  },
  {
    "data_zmiany": "30-07-2022",
    "cena_pln_m3": 6895
  },
  {
    "data_zmiany": "29-07-2022",
    "cena_pln_m3": 6894
  },
  {
    "data_zmiany": "28-07-2022",
    "cena_pln_m3": 6866
  },
  {
    "data_zmiany": "27-07-2022",
    "cena_pln_m3": 6840
  },
  {
    "data_zmiany": "26-07-2022",
    "cena_pln_m3": 6848
  },
  {
    "data_zmiany": "23-07-2022",
    "cena_pln_m3": 6883
  },
  {
    "data_zmiany": "22-07-2022",
    "cena_pln_m3": 6937
  },
  {
    "data_zmiany": "21-07-2022",
    "cena_pln_m3": 6996
  },
  {
    "data_zmiany": "20-07-2022",
    "cena_pln_m3": 7041
  },
  {
    "data_zmiany": "19-07-2022",
    "cena_pln_m3": 7090
  },
  {
    "data_zmiany": "16-07-2022",
    "cena_pln_m3": 7137
  },
  {
    "data_zmiany": "15-07-2022",
    "cena_pln_m3": 7053
  },
  {
    "data_zmiany": "14-07-2022",
    "cena_pln_m3": 7080
  },
  {
    "data_zmiany": "13-07-2022",
    "cena_pln_m3": 7040
  },
  {
    "data_zmiany": "12-07-2022",
    "cena_pln_m3": 7074
  },
  {
    "data_zmiany": "09-07-2022",
    "cena_pln_m3": 6951
  },
  {
    "data_zmiany": "08-07-2022",
    "cena_pln_m3": 6976
  },
  {
    "data_zmiany": "07-07-2022",
    "cena_pln_m3": 6979
  },
  {
    "data_zmiany": "06-07-2022",
    "cena_pln_m3": 7046
  },
  {
    "data_zmiany": "05-07-2022",
    "cena_pln_m3": 7114
  },
  {
    "data_zmiany": "02-07-2022",
    "cena_pln_m3": 7095
  },
  {
    "data_zmiany": "01-07-2022",
    "cena_pln_m3": 7044
  },
  {
    "data_zmiany": "30-06-2022",
    "cena_pln_m3": 7140
  },
  {
    "data_zmiany": "29-06-2022",
    "cena_pln_m3": 7177
  },
  {
    "data_zmiany": "28-06-2022",
    "cena_pln_m3": 7245
  },
  {
    "data_zmiany": "25-06-2022",
    "cena_pln_m3": 7258
  },
  {
    "data_zmiany": "24-06-2022",
    "cena_pln_m3": 7274
  },
  {
    "data_zmiany": "23-06-2022",
    "cena_pln_m3": 7299
  },
  {
    "data_zmiany": "22-06-2022",
    "cena_pln_m3": 7301
  },
  {
    "data_zmiany": "21-06-2022",
    "cena_pln_m3": 7378
  },
  {
    "data_zmiany": "18-06-2022",
    "cena_pln_m3": 7374
  },
  {
    "data_zmiany": "16-06-2022",
    "cena_pln_m3": 7358
  },
  {
    "data_zmiany": "15-06-2022",
    "cena_pln_m3": 7261
  },
  {
    "data_zmiany": "14-06-2022",
    "cena_pln_m3": 7198
  },
  {
    "data_zmiany": "11-06-2022",
    "cena_pln_m3": 7167
  },
  {
    "data_zmiany": "10-06-2022",
    "cena_pln_m3": 7098
  },
  {
    "data_zmiany": "09-06-2022",
    "cena_pln_m3": 7254
  },
  {
    "data_zmiany": "08-06-2022",
    "cena_pln_m3": 7130
  },
  {
    "data_zmiany": "07-06-2022",
    "cena_pln_m3": 7166
  },
  {
    "data_zmiany": "02-06-2022",
    "cena_pln_m3": 7172
  },
  {
    "data_zmiany": "01-06-2022",
    "cena_pln_m3": 6912
  },
  {
    "data_zmiany": "31-05-2022",
    "cena_pln_m3": 6754
  },
  {
    "data_zmiany": "28-05-2022",
    "cena_pln_m3": 6711
  },
  {
    "data_zmiany": "27-05-2022",
    "cena_pln_m3": 6704
  },
  {
    "data_zmiany": "26-05-2022",
    "cena_pln_m3": 6502
  },
  {
    "data_zmiany": "25-05-2022",
    "cena_pln_m3": 6421
  },
  {
    "data_zmiany": "24-05-2022",
    "cena_pln_m3": 6405
  },
  {
    "data_zmiany": "21-05-2022",
    "cena_pln_m3": 6457
  },
  {
    "data_zmiany": "20-05-2022",
    "cena_pln_m3": 6523
  },
  {
    "data_zmiany": "19-05-2022",
    "cena_pln_m3": 6570
  },
  {
    "data_zmiany": "18-05-2022",
    "cena_pln_m3": 6625
  },
  {
    "data_zmiany": "17-05-2022",
    "cena_pln_m3": 6653
  },
  {
    "data_zmiany": "14-05-2022",
    "cena_pln_m3": 6677
  },
  {
    "data_zmiany": "13-05-2022",
    "cena_pln_m3": 6594
  },
  {
    "data_zmiany": "12-05-2022",
    "cena_pln_m3": 6582
  },
  {
    "data_zmiany": "11-05-2022",
    "cena_pln_m3": 6532
  },
  {
    "data_zmiany": "10-05-2022",
    "cena_pln_m3": 6550
  },
  {
    "data_zmiany": "07-05-2022",
    "cena_pln_m3": 6792
  },
  {
    "data_zmiany": "06-05-2022",
    "cena_pln_m3": 6844
  },
  {
    "data_zmiany": "05-05-2022",
    "cena_pln_m3": 6919
  },
  {
    "data_zmiany": "30-04-2022",
    "cena_pln_m3": 6901
  },
  {
    "data_zmiany": "29-04-2022",
    "cena_pln_m3": 6944
  },
  {
    "data_zmiany": "28-04-2022",
    "cena_pln_m3": 6889
  },
  {
    "data_zmiany": "27-04-2022",
    "cena_pln_m3": 6667
  },
  {
    "data_zmiany": "26-04-2022",
    "cena_pln_m3": 6591
  },
  {
    "data_zmiany": "23-04-2022",
    "cena_pln_m3": 6666
  },
  {
    "data_zmiany": "22-04-2022",
    "cena_pln_m3": 6627
  },
  {
    "data_zmiany": "21-04-2022",
    "cena_pln_m3": 6683
  },
  {
    "data_zmiany": "20-04-2022",
    "cena_pln_m3": 6646
  },
  {
    "data_zmiany": "15-04-2022",
    "cena_pln_m3": 6666
  },
  {
    "data_zmiany": "14-04-2022",
    "cena_pln_m3": 6491
  },
  {
    "data_zmiany": "13-04-2022",
    "cena_pln_m3": 6403
  },
  {
    "data_zmiany": "12-04-2022",
    "cena_pln_m3": 6237
  },
  {
    "data_zmiany": "09-04-2022",
    "cena_pln_m3": 6311
  },
  {
    "data_zmiany": "08-04-2022",
    "cena_pln_m3": 6356
  },
  {
    "data_zmiany": "07-04-2022",
    "cena_pln_m3": 6415
  },
  {
    "data_zmiany": "06-04-2022",
    "cena_pln_m3": 6460
  },
  {
    "data_zmiany": "05-04-2022",
    "cena_pln_m3": 6554
  },
  {
    "data_zmiany": "02-04-2022",
    "cena_pln_m3": 6518
  },
  {
    "data_zmiany": "01-04-2022",
    "cena_pln_m3": 6652
  },
  {
    "data_zmiany": "31-03-2022",
    "cena_pln_m3": 6836
  },
  {
    "data_zmiany": "30-03-2022",
    "cena_pln_m3": 6991
  },
  {
    "data_zmiany": "29-03-2022",
    "cena_pln_m3": 7091
  },
  {
    "data_zmiany": "26-03-2022",
    "cena_pln_m3": 7187
  },
  {
    "data_zmiany": "25-03-2022",
    "cena_pln_m3": 7254
  },
  {
    "data_zmiany": "24-03-2022",
    "cena_pln_m3": 7198
  },
  {
    "data_zmiany": "23-03-2022",
    "cena_pln_m3": 6847
  },
  {
    "data_zmiany": "22-03-2022",
    "cena_pln_m3": 6766
  },
  {
    "data_zmiany": "19-03-2022",
    "cena_pln_m3": 6482
  },
  {
    "data_zmiany": "18-03-2022",
    "cena_pln_m3": 6413
  },
  {
    "data_zmiany": "17-03-2022",
    "cena_pln_m3": 6173
  },
  {
    "data_zmiany": "16-03-2022",
    "cena_pln_m3": 6354
  },
  {
    "data_zmiany": "15-03-2022",
    "cena_pln_m3": 6701
  },
  {
    "data_zmiany": "12-03-2022",
    "cena_pln_m3": 6922
  },
  {
    "data_zmiany": "11-03-2022",
    "cena_pln_m3": 7060
  },
  {
    "data_zmiany": "10-03-2022",
    "cena_pln_m3": 7348
  },
  {
    "data_zmiany": "09-03-2022",
    "cena_pln_m3": 7704
  },
  {
    "data_zmiany": "08-03-2022",
    "cena_pln_m3": 7276
  },
  {
    "data_zmiany": "05-03-2022",
    "cena_pln_m3": 6632
  },
  {
    "data_zmiany": "04-03-2022",
    "cena_pln_m3": 6367
  },
  {
    "data_zmiany": "03-03-2022",
    "cena_pln_m3": 6203
  },
  {
    "data_zmiany": "02-03-2022",
    "cena_pln_m3": 5833
  },
  {
    "data_zmiany": "01-03-2022",
    "cena_pln_m3": 5530
  },
  {
    "data_zmiany": "26-02-2022",
    "cena_pln_m3": 5436
  },
  {
    "data_zmiany": "25-02-2022",
    "cena_pln_m3": 5504
  },
  {
    "data_zmiany": "24-02-2022",
    "cena_pln_m3": 5152
  },
  {
    "data_zmiany": "23-02-2022",
    "cena_pln_m3": 5158
  },
  {
    "data_zmiany": "22-02-2022",
    "cena_pln_m3": 5084
  },
  {
    "data_zmiany": "19-02-2022",
    "cena_pln_m3": 5060
  },
  {
    "data_zmiany": "18-02-2022",
    "cena_pln_m3": 5057
  },
  {
    "data_zmiany": "17-02-2022",
    "cena_pln_m3": 5075
  },
  {
    "data_zmiany": "16-02-2022",
    "cena_pln_m3": 5080
  },
  {
    "data_zmiany": "15-02-2022",
    "cena_pln_m3": 5134
  },
  {
    "data_zmiany": "12-02-2022",
    "cena_pln_m3": 5024
  },
  {
    "data_zmiany": "11-02-2022",
    "cena_pln_m3": 4994
  },
  {
    "data_zmiany": "10-02-2022",
    "cena_pln_m3": 4995
  },
  {
    "data_zmiany": "09-02-2022",
    "cena_pln_m3": 5004
  },
  {
    "data_zmiany": "08-02-2022",
    "cena_pln_m3": 5050
  },
  {
    "data_zmiany": "05-02-2022",
    "cena_pln_m3": 5042
  },
  {
    "data_zmiany": "04-02-2022",
    "cena_pln_m3": 4996
  },
  {
    "data_zmiany": "03-02-2022",
    "cena_pln_m3": 4984
  },
  {
    "data_zmiany": "02-02-2022",
    "cena_pln_m3": 4988
  },
  {
    "data_zmiany": "01-02-2022",
    "cena_pln_m3": 4993
  },
  {
    "data_zmiany": "29-01-2022",
    "cena_pln_m3": 5002
  },
  {
    "data_zmiany": "28-01-2022",
    "cena_pln_m3": 4934
  },
  {
    "data_zmiany": "27-01-2022",
    "cena_pln_m3": 4928
  },
  {
    "data_zmiany": "26-01-2022",
    "cena_pln_m3": 4844
  },
  {
    "data_zmiany": "25-01-2022",
    "cena_pln_m3": 4827
  },
  {
    "data_zmiany": "22-01-2022",
    "cena_pln_m3": 4843
  },
  {
    "data_zmiany": "21-01-2022",
    "cena_pln_m3": 4846
  },
  {
    "data_zmiany": "20-01-2022",
    "cena_pln_m3": 4831
  },
  {
    "data_zmiany": "19-01-2022",
    "cena_pln_m3": 4799
  },
  {
    "data_zmiany": "18-01-2022",
    "cena_pln_m3": 4773
  },
  {
    "data_zmiany": "15-01-2022",
    "cena_pln_m3": 4765
  },
  {
    "data_zmiany": "14-01-2022",
    "cena_pln_m3": 4761
  },
  {
    "data_zmiany": "13-01-2022",
    "cena_pln_m3": 4758
  },
  {
    "data_zmiany": "12-01-2022",
    "cena_pln_m3": 4747
  },
  {
    "data_zmiany": "11-01-2022",
    "cena_pln_m3": 4731
  },
  {
    "data_zmiany": "08-01-2022",
    "cena_pln_m3": 4713
  },
  {
    "data_zmiany": "06-01-2022",
    "cena_pln_m3": 4672
  },
  {
    "data_zmiany": "05-01-2022",
    "cena_pln_m3": 4641
  },
  {
    "data_zmiany": "01-01-2022",
    "cena_pln_m3": 4622
  }
]